{"username": "WhizNL", "white": {"children": [{"count": 34, "win": 18, "games": [0, 2, 4, 6, 8, 10, 13, 16, 17, 20, 23, 24, 27, 28, 30, 35, 38, 40, 43, 45, 46, 49, 50, 52, 54, 56, 58, 60, 61, 62, 65, 66, 68, 69], "draw": 2, "lose": 14, "children": [{"count": 1, "win": 1, "games": [17], "draw": 0, "lose": 0, "children": [{"count": 1, "win": 1, "games": [17], "draw": 0, "lose": 0, "children": [{"count": 1, "win": 1, "games": [17], "draw": 0, "lose": 0, "children": [{"count": 1, "win": 1, "games": [17], "draw": 0, "lose": 0, "children": [{"count": 1, "win": 1, "games": [17], "draw": 0, "lose": 0, "children": [{"count": 1, "win": 1, "games": [17], "draw": 0, "lose": 0, "children": [{"count": 1, "win": 1, "games": [17], "draw": 0, "lose": 0, "children": [{"count": 1, "win": 1, "games": [17], "draw": 0, "lose": 0, "children": [{"count": 1, "win": 1, "games": [17], "draw": 0, "lose": 0, "children": [{"count": 1, "win": 1, "games": [17], "draw": 0, "lose": 0, "children": [], "move": "b3"}], "move": "b5"}], "move": "e4"}], "move": "a6"}], "move": "Nf3"}], "move": "c6"}], "move": "Nc3"}], "move": "e6"}], "move": "c4"}], "move": "h6"}, {"count": 2, "win": 0, "games": [49, 13], "draw": 0, "lose": 2, "children": [{"count": 1, "win": 0, "games": [49], "draw": 0, "lose": 1, "children": [{"count": 1, "win": 0, "games": [49], "draw": 0, "lose": 1, "children": [{"count": 1, "win": 0, "games": [49], "draw": 0, "lose": 1, "children": [{"count": 1, "win": 0, "games": [49], "draw": 0, "lose": 1, "children": [{"count": 1, "win": 0, "games": [49], "draw": 0, "lose": 1, "children": [{"count": 1, "win": 0, "games": [49], "draw": 0, "lose": 1, "children": [{"count": 1, "win": 0, "games": [49], "draw": 0, "lose": 1, "children": [{"count": 1, "win": 0, "games": [49], "draw": 0, "lose": 1, "children": [{"count": 1, "win": 0, "games": [49], "draw": 0, "lose": 1, "children": [], "move": "d5"}], "move": "Qc8"}], "move": "Qe2"}], "move": "c5"}], "move": "a3"}], "move": "Na6"}], "move": "Bd3"}], "move": "Bb7"}], "move": "e4"}, {"count": 1, "win": 0, "games": [13], "draw": 0, "lose": 1, "children": [{"count": 1, "win": 0, "games": [13], "draw": 0, "lose": 1, "children": [{"count": 1, "win": 0, "games": [13], "draw": 0, "lose": 1, "children": [{"count": 1, "win": 0, "games": [13], "draw": 0, "lose": 1, "children": [{"count": 1, "win": 0, "games": [13], "draw": 0, "lose": 1, "children": [{"count": 1, "win": 0, "games": [13], "draw": 0, "lose": 1, "children": [{"count": 1, "win": 0, "games": [13], "draw": 0, "lose": 1, "children": [{"count": 1, "win": 0, "games": [13], "draw": 0, "lose": 1, "children": [{"count": 1, "win": 0, "games": [13], "draw": 0, "lose": 1, "children": [], "move": "Nf3"}], "move": "Bd6"}], "move": "e4"}], "move": "e6"}], "move": "d5"}], "move": "c5"}], "move": "Nc3"}], "move": "Bb7"}], "move": "c4"}], "move": "b6"}, {"count": 1, "win": 1, "games": [35], "draw": 0, "lose": 0, "children": [{"count": 1, "win": 1, "games": [35], "draw": 0, "lose": 0, "children": [{"count": 1, "win": 1, "games": [35], "draw": 0, "lose": 0, "children": [{"count": 1, "win": 1, "games": [35], "draw": 0, "lose": 0, "children": [{"count": 1, "win": 1, "games": [35], "draw": 0, "lose": 0, "children": [{"count": 1, "win": 1, "games": [35], "draw": 0, "lose": 0, "children": [{"count": 1, "win": 1, "games": [35], "draw": 0, "lose": 0, "children": [{"count": 1, "win": 1, "games": [35], "draw": 0, "lose": 0, "children": [{"count": 1, "win": 1, "games": [35], "draw": 0, "lose": 0, "children": [{"count": 1, "win": 1, "games": [35], "draw": 0, "lose": 0, "children": [], "move": "b3"}], "move": "Ne5"}], "move": "Nfd2"}], "move": "e4"}], "move": "d5"}], "move": "e5"}], "move": "c4"}], "move": "f6"}], "move": "Nf3"}], "move": "Nc6"}, {"count": 16, "win": 8, "games": [0, 65, 2, 66, 68, 69, 8, 10, 45, 46, 16, 50, 20, 23, 28, 60], "draw": 2, "lose": 6, "children": [{"count": 16, "win": 8, "games": [0, 65, 2, 66, 68, 69, 8, 10, 45, 46, 16, 50, 20, 23, 28, 60], "draw": 2, "lose": 6, "children": [{"count": 4, "win": 3, "games": [16, 2, 66, 28], "draw": 0, "lose": 1, "children": [{"count": 4, "win": 3, "games": [16, 2, 66, 28], "draw": 0, "lose": 1, "children": [{"count": 1, "win": 0, "games": [16], "draw": 0, "lose": 1, "children": [{"count": 1, "win": 0, "games": [16], "draw": 0, "lose": 1, "children": [{"count": 1, "win": 0, "games": [16], "draw": 0, "lose": 1, "children": [{"count": 1, "win": 0, "games": [16], "draw": 0, "lose": 1, "children": [{"count": 1, "win": 0, "games": [16], "draw": 0, "lose": 1, "children": [{"count": 1, "win": 0, "games": [16], "draw": 0, "lose": 1, "children": [], "move": "a4"}], "move": "a6"}], "move": "Bxc4"}], "move": "Bd7"}], "move": "Nc3"}], "move": "e6"}, {"count": 1, "win": 1, "games": [2], "draw": 0, "lose": 0, "children": [{"count": 1, "win": 1, "games": [2], "draw": 0, "lose": 0, "children": [{"count": 1, "win": 1, "games": [2], "draw": 0, "lose": 0, "children": [{"count": 1, "win": 1, "games": [2], "draw": 0, "lose": 0, "children": [{"count": 1, "win": 1, "games": [2], "draw": 0, "lose": 0, "children": [{"count": 1, "win": 1, "games": [2], "draw": 0, "lose": 0, "children": [], "move": "Nf3"}], "move": "Nc6"}], "move": "Nc3"}], "move": "Bb4+"}], "move": "Bxc4"}], "move": "e5"}, {"count": 1, "win": 1, "games": [28], "draw": 0, "lose": 0, "children": [{"count": 1, "win": 1, "games": [28], "draw": 0, "lose": 0, "children": [{"count": 1, "win": 1, "games": [28], "draw": 0, "lose": 0, "children": [{"count": 1, "win": 1, "games": [28], "draw": 0, "lose": 0, "children": [{"count": 1, "win": 1, "games": [28], "draw": 0, "lose": 0, "children": [{"count": 1, "win": 1, "games": [28], "draw": 0, "lose": 0, "children": [], "move": "Nc3"}], "move": "Nc6"}], "move": "a4"}], "move": "a6"}], "move": "Bxc4"}], "move": "Bf5"}, {"count": 1, "win": 1, "games": [66], "draw": 0, "lose": 0, "children": [{"count": 1, "win": 1, "games": [66], "draw": 0, "lose": 0, "children": [{"count": 1, "win": 1, "games": [66], "draw": 0, "lose": 0, "children": [{"count": 1, "win": 1, "games": [66], "draw": 0, "lose": 0, "children": [{"count": 1, "win": 1, "games": [66], "draw": 0, "lose": 0, "children": [{"count": 1, "win": 1, "games": [66], "draw": 0, "lose": 0, "children": [], "move": "Nc3"}], "move": "Ne4"}], "move": "Nf3"}], "move": "Nf6"}], "move": "Bxc4"}], "move": "Nc6"}], "move": "e3"}], "move": "dxc4"}, {"count": 7, "win": 2, "games": [0, 68, 69, 50, 20, 23, 60], "draw": 2, "lose": 3, "children": [{"count": 7, "win": 2, "games": [0, 68, 69, 50, 20, 23, 60], "draw": 2, "lose": 3, "children": [{"count": 2, "win": 0, "games": [68, 69], "draw": 0, "lose": 2, "children": [{"count": 2, "win": 0, "games": [68, 69], "draw": 0, "lose": 2, "children": [{"count": 1, "win": 0, "games": [69], "draw": 0, "lose": 1, "children": [{"count": 1, "win": 0, "games": [69], "draw": 0, "lose": 1, "children": [{"count": 1, "win": 0, "games": [69], "draw": 0, "lose": 1, "children": [{"count": 1, "win": 0, "games": [69], "draw": 0, "lose": 1, "children": [], "move": "a3"}], "move": "Nc6"}], "move": "e3"}], "move": "Nf6"}, {"count": 1, "win": 0, "games": [68], "draw": 0, "lose": 1, "children": [{"count": 1, "win": 0, "games": [68], "draw": 0, "lose": 1, "children": [{"count": 1, "win": 0, "games": [68], "draw": 0, "lose": 1, "children": [{"count": 1, "win": 0, "games": [68], "draw": 0, "lose": 1, "children": [], "move": "e3"}], "move": "dxc4"}], "move": "bxc3"}], "move": "Bxc3+"}], "move": "Nf3"}], "move": "Bb4"}, {"count": 5, "win": 2, "games": [0, 50, 20, 60, 23], "draw": 2, "lose": 1, "children": [{"count": 4, "win": 2, "games": [50, 20, 60, 23], "draw": 1, "lose": 1, "children": [{"count": 1, "win": 0, "games": [23], "draw": 0, "lose": 1, "children": [{"count": 1, "win": 0, "games": [23], "draw": 0, "lose": 1, "children": [{"count": 1, "win": 0, "games": [23], "draw": 0, "lose": 1, "children": [{"count": 1, "win": 0, "games": [23], "draw": 0, "lose": 1, "children": [], "move": "Nxd4"}], "move": "cxd4"}], "move": "e3"}], "move": "c5"}, {"count": 2, "win": 1, "games": [50, 20], "draw": 1, "lose": 0, "children": [{"count": 2, "win": 1, "games": [50, 20], "draw": 1, "lose": 0, "children": [{"count": 2, "win": 1, "games": [50, 20], "draw": 1, "lose": 0, "children": [{"count": 2, "win": 1, "games": [50, 20], "draw": 1, "lose": 0, "children": [], "move": "a3"}], "move": "Nbd7"}], "move": "e3"}], "move": "c6"}, {"count": 1, "win": 1, "games": [60], "draw": 0, "lose": 0, "children": [{"count": 1, "win": 1, "games": [60], "draw": 0, "lose": 0, "children": [{"count": 1, "win": 1, "games": [60], "draw": 0, "lose": 0, "children": [{"count": 1, "win": 1, "games": [60], "draw": 0, "lose": 0, "children": [], "move": "a3"}], "move": "Nc6"}], "move": "Bg5"}], "move": "Bb4"}], "move": "Nf3"}, {"count": 1, "win": 0, "games": [0], "draw": 1, "lose": 0, "children": [{"count": 1, "win": 0, "games": [0], "draw": 1, "lose": 0, "children": [{"count": 1, "win": 0, "games": [0], "draw": 1, "lose": 0, "children": [{"count": 1, "win": 0, "games": [0], "draw": 1, "lose": 0, "children": [{"count": 1, "win": 0, "games": [0], "draw": 1, "lose": 0, "children": [], "move": "e3"}], "move": "O-O"}], "move": "Nf3"}], "move": "Bb4"}], "move": "Bg5"}], "move": "Nf6"}], "move": "Nc3"}], "move": "e6"}, {"count": 2, "win": 1, "games": [8, 10], "draw": 0, "lose": 1, "children": [{"count": 2, "win": 1, "games": [8, 10], "draw": 0, "lose": 1, "children": [{"count": 2, "win": 1, "games": [8, 10], "draw": 0, "lose": 1, "children": [{"count": 2, "win": 1, "games": [8, 10], "draw": 0, "lose": 1, "children": [{"count": 2, "win": 1, "games": [8, 10], "draw": 0, "lose": 1, "children": [{"count": 1, "win": 1, "games": [8], "draw": 0, "lose": 0, "children": [{"count": 1, "win": 1, "games": [8], "draw": 0, "lose": 0, "children": [{"count": 1, "win": 1, "games": [8], "draw": 0, "lose": 0, "children": [], "move": "e3"}], "move": "Nc6"}], "move": "h3"}, {"count": 1, "win": 0, "games": [10], "draw": 0, "lose": 1, "children": [{"count": 1, "win": 0, "games": [10], "draw": 0, "lose": 1, "children": [{"count": 1, "win": 0, "games": [10], "draw": 0, "lose": 1, "children": [], "move": "g3"}], "move": "Bg4"}], "move": "e3"}], "move": "c5"}], "move": "Nf3"}], "move": "d4"}], "move": "dxe5"}], "move": "e5"}, {"count": 2, "win": 2, "games": [65, 46], "draw": 0, "lose": 0, "children": [{"count": 2, "win": 2, "games": [65, 46], "draw": 0, "lose": 0, "children": [{"count": 2, "win": 2, "games": [65, 46], "draw": 0, "lose": 0, "children": [{"count": 1, "win": 1, "games": [65], "draw": 0, "lose": 0, "children": [{"count": 1, "win": 1, "games": [65], "draw": 0, "lose": 0, "children": [{"count": 1, "win": 1, "games": [65], "draw": 0, "lose": 0, "children": [{"count": 1, "win": 1, "games": [65], "draw": 0, "lose": 0, "children": [{"count": 1, "win": 1, "games": [65], "draw": 0, "lose": 0, "children": [], "move": "Nc3"}], "move": "Bd6"}], "move": "a3"}], "move": "e6"}], "move": "Nf3"}, {"count": 1, "win": 1, "games": [46], "draw": 0, "lose": 0, "children": [{"count": 1, "win": 1, "games": [46], "draw": 0, "lose": 0, "children": [{"count": 1, "win": 1, "games": [46], "draw": 0, "lose": 0, "children": [{"count": 1, "win": 1, "games": [46], "draw": 0, "lose": 0, "children": [{"count": 1, "win": 1, "games": [46], "draw": 0, "lose": 0, "children": [], "move": "Nf3"}], "move": "e5"}], "move": "Nc3"}], "move": "Nb6"}], "move": "e4"}], "move": "Nxd5"}], "move": "cxd5"}], "move": "Nf6"}, {"count": 1, "win": 0, "games": [45], "draw": 0, "lose": 1, "children": [{"count": 1, "win": 0, "games": [45], "draw": 0, "lose": 1, "children": [{"count": 1, "win": 0, "games": [45], "draw": 0, "lose": 1, "children": [{"count": 1, "win": 0, "games": [45], "draw": 0, "lose": 1, "children": [{"count": 1, "win": 0, "games": [45], "draw": 0, "lose": 1, "children": [{"count": 1, "win": 0, "games": [45], "draw": 0, "lose": 1, "children": [{"count": 1, "win": 0, "games": [45], "draw": 0, "lose": 1, "children": [{"count": 1, "win": 0, "games": [45], "draw": 0, "lose": 1, "children": [], "move": "Nf3"}], "move": "Bg6"}], "move": "e4"}], "move": "Qd8"}], "move": "Nc3"}], "move": "Qxd5"}], "move": "cxd5"}], "move": "Bf5"}], "move": "c4"}], "move": "d5"}, {"count": 1, "win": 0, "games": [24], "draw": 0, "lose": 1, "children": [{"count": 1, "win": 0, "games": [24], "draw": 0, "lose": 1, "children": [{"count": 1, "win": 0, "games": [24], "draw": 0, "lose": 1, "children": [{"count": 1, "win": 0, "games": [24], "draw": 0, "lose": 1, "children": [{"count": 1, "win": 0, "games": [24], "draw": 0, "lose": 1, "children": [{"count": 1, "win": 0, "games": [24], "draw": 0, "lose": 1, "children": [{"count": 1, "win": 0, "games": [24], "draw": 0, "lose": 1, "children": [{"count": 1, "win": 0, "games": [24], "draw": 0, "lose": 1, "children": [{"count": 1, "win": 0, "games": [24], "draw": 0, "lose": 1, "children": [{"count": 1, "win": 0, "games": [24], "draw": 0, "lose": 1, "children": [], "move": "h4"}], "move": "h5"}], "move": "g3"}], "move": "Be7"}], "move": "Nf3"}], "move": "e6"}], "move": "Nc3"}], "move": "Nf6"}], "move": "c4"}], "move": "f5"}, {"count": 5, "win": 3, "games": [40, 56, 4, 52, 61], "draw": 0, "lose": 2, "children": [{"count": 5, "win": 3, "games": [40, 56, 4, 52, 61], "draw": 0, "lose": 2, "children": [{"count": 1, "win": 1, "games": [61], "draw": 0, "lose": 0, "children": [{"count": 1, "win": 1, "games": [61], "draw": 0, "lose": 0, "children": [{"count": 1, "win": 1, "games": [61], "draw": 0, "lose": 0, "children": [{"count": 1, "win": 1, "games": [61], "draw": 0, "lose": 0, "children": [{"count": 1, "win": 1, "games": [61], "draw": 0, "lose": 0, "children": [{"count": 1, "win": 1, "games": [61], "draw": 0, "lose": 0, "children": [{"count": 1, "win": 1, "games": [61], "draw": 0, "lose": 0, "children": [{"count": 1, "win": 1, "games": [61], "draw": 0, "lose": 0, "children": [], "move": "Bg5"}], "move": "Ng4"}], "move": "dxe5"}], "move": "e5"}], "move": "Nf3"}], "move": "Nc6"}], "move": "Nc3"}], "move": "Nf6"}, {"count": 2, "win": 1, "games": [40, 56], "draw": 0, "lose": 1, "children": [{"count": 2, "win": 1, "games": [40, 56], "draw": 0, "lose": 1, "children": [{"count": 1, "win": 0, "games": [56], "draw": 0, "lose": 1, "children": [{"count": 1, "win": 0, "games": [56], "draw": 0, "lose": 1, "children": [{"count": 1, "win": 0, "games": [56], "draw": 0, "lose": 1, "children": [{"count": 1, "win": 0, "games": [56], "draw": 0, "lose": 1, "children": [{"count": 1, "win": 0, "games": [56], "draw": 0, "lose": 1, "children": [{"count": 1, "win": 0, "games": [56], "draw": 0, "lose": 1, "children": [], "move": "Nf3"}], "move": "Be7"}], "move": "e4"}], "move": "d6"}], "move": "Nc3"}], "move": "e5"}, {"count": 1, "win": 1, "games": [40], "draw": 0, "lose": 0, "children": [{"count": 1, "win": 1, "games": [40], "draw": 0, "lose": 0, "children": [{"count": 1, "win": 1, "games": [40], "draw": 0, "lose": 0, "children": [{"count": 1, "win": 1, "games": [40], "draw": 0, "lose": 0, "children": [{"count": 1, "win": 1, "games": [40], "draw": 0, "lose": 0, "children": [{"count": 1, "win": 1, "games": [40], "draw": 0, "lose": 0, "children": [], "move": "cxd5"}], "move": "exd5"}], "move": "e4"}], "move": "Be7"}], "move": "Nc3"}], "move": "Nf6"}], "move": "d5"}], "move": "c5"}, {"count": 1, "win": 1, "games": [52], "draw": 0, "lose": 0, "children": [{"count": 1, "win": 1, "games": [52], "draw": 0, "lose": 0, "children": [{"count": 1, "win": 1, "games": [52], "draw": 0, "lose": 0, "children": [{"count": 1, "win": 1, "games": [52], "draw": 0, "lose": 0, "children": [{"count": 1, "win": 1, "games": [52], "draw": 0, "lose": 0, "children": [{"count": 1, "win": 1, "games": [52], "draw": 0, "lose": 0, "children": [{"count": 1, "win": 1, "games": [52], "draw": 0, "lose": 0, "children": [{"count": 1, "win": 1, "games": [52], "draw": 0, "lose": 0, "children": [], "move": "e3"}], "move": "e5"}], "move": "a3"}], "move": "Nc6"}], "move": "Nf3"}], "move": "Ba5"}], "move": "Nc3"}], "move": "Bb4+"}, {"count": 1, "win": 0, "games": [4], "draw": 0, "lose": 1, "children": [{"count": 1, "win": 0, "games": [4], "draw": 0, "lose": 1, "children": [{"count": 1, "win": 0, "games": [4], "draw": 0, "lose": 1, "children": [{"count": 1, "win": 0, "games": [4], "draw": 0, "lose": 1, "children": [{"count": 1, "win": 0, "games": [4], "draw": 0, "lose": 1, "children": [{"count": 1, "win": 0, "games": [4], "draw": 0, "lose": 1, "children": [{"count": 1, "win": 0, "games": [4], "draw": 0, "lose": 1, "children": [{"count": 1, "win": 0, "games": [4], "draw": 0, "lose": 1, "children": [], "move": "g3"}], "move": "Ng6"}], "move": "Nf3"}], "move": "Bb7"}], "move": "Nc3"}], "move": "b6"}], "move": "e4"}], "move": "Ne7"}], "move": "c4"}], "move": "e6"}, {"count": 6, "win": 3, "games": [38, 6, 43, 58, 27, 30], "draw": 0, "lose": 3, "children": [{"count": 6, "win": 3, "games": [38, 6, 43, 58, 27, 30], "draw": 0, "lose": 3, "children": [{"count": 1, "win": 1, "games": [30], "draw": 0, "lose": 0, "children": [{"count": 1, "win": 1, "games": [30], "draw": 0, "lose": 0, "children": [{"count": 1, "win": 1, "games": [30], "draw": 0, "lose": 0, "children": [{"count": 1, "win": 1, "games": [30], "draw": 0, "lose": 0, "children": [{"count": 1, "win": 1, "games": [30], "draw": 0, "lose": 0, "children": [{"count": 1, "win": 1, "games": [30], "draw": 0, "lose": 0, "children": [{"count": 1, "win": 1, "games": [30], "draw": 0, "lose": 0, "children": [{"count": 1, "win": 1, "games": [30], "draw": 0, "lose": 0, "children": [], "move": "a3"}], "move": "Qb4"}], "move": "e3"}], "move": "Qc4"}], "move": "Nc3"}], "move": "Qxd5"}], "move": "cxd5"}], "move": "d5"}, {"count": 1, "win": 0, "games": [38], "draw": 0, "lose": 1, "children": [{"count": 1, "win": 0, "games": [38], "draw": 0, "lose": 1, "children": [{"count": 1, "win": 0, "games": [38], "draw": 0, "lose": 1, "children": [{"count": 1, "win": 0, "games": [38], "draw": 0, "lose": 1, "children": [{"count": 1, "win": 0, "games": [38], "draw": 0, "lose": 1, "children": [{"count": 1, "win": 0, "games": [38], "draw": 0, "lose": 1, "children": [{"count": 1, "win": 0, "games": [38], "draw": 0, "lose": 1, "children": [{"count": 1, "win": 0, "games": [38], "draw": 0, "lose": 1, "children": [], "move": "a3"}], "move": "Bb4"}], "move": "e3"}], "move": "c6"}], "move": "Nf3"}], "move": "d5"}], "move": "Nc3"}], "move": "e6"}, {"count": 1, "win": 0, "games": [27], "draw": 0, "lose": 1, "children": [{"count": 1, "win": 0, "games": [27], "draw": 0, "lose": 1, "children": [{"count": 1, "win": 0, "games": [27], "draw": 0, "lose": 1, "children": [{"count": 1, "win": 0, "games": [27], "draw": 0, "lose": 1, "children": [{"count": 1, "win": 0, "games": [27], "draw": 0, "lose": 1, "children": [{"count": 1, "win": 0, "games": [27], "draw": 0, "lose": 1, "children": [{"count": 1, "win": 0, "games": [27], "draw": 0, "lose": 1, "children": [{"count": 1, "win": 0, "games": [27], "draw": 0, "lose": 1, "children": [], "move": "Nbd2"}], "move": "Bb4+"}], "move": "Bf4"}], "move": "Nc6"}], "move": "Nf3"}], "move": "Ng4"}], "move": "dxe5"}], "move": "e5"}, {"count": 3, "win": 2, "games": [58, 43, 6], "draw": 0, "lose": 1, "children": [{"count": 3, "win": 2, "games": [58, 43, 6], "draw": 0, "lose": 1, "children": [{"count": 3, "win": 2, "games": [58, 43, 6], "draw": 0, "lose": 1, "children": [{"count": 1, "win": 1, "games": [58], "draw": 0, "lose": 0, "children": [{"count": 1, "win": 1, "games": [58], "draw": 0, "lose": 0, "children": [{"count": 1, "win": 1, "games": [58], "draw": 0, "lose": 0, "children": [{"count": 1, "win": 1, "games": [58], "draw": 0, "lose": 0, "children": [{"count": 1, "win": 1, "games": [58], "draw": 0, "lose": 0, "children": [], "move": "Bg2"}], "move": "O-O"}], "move": "g3"}], "move": "d6"}], "move": "Nf3"}, {"count": 2, "win": 1, "games": [43, 6], "draw": 0, "lose": 1, "children": [{"count": 2, "win": 1, "games": [43, 6], "draw": 0, "lose": 1, "children": [{"count": 2, "win": 1, "games": [43, 6], "draw": 0, "lose": 1, "children": [{"count": 1, "win": 1, "games": [6], "draw": 0, "lose": 0, "children": [{"count": 1, "win": 1, "games": [6], "draw": 0, "lose": 0, "children": [], "move": "dxe5"}], "move": "e5"}, {"count": 1, "win": 0, "games": [43], "draw": 0, "lose": 1, "children": [{"count": 1, "win": 0, "games": [43], "draw": 0, "lose": 1, "children": [], "move": "Be2"}], "move": "Nc6"}], "move": "Nf3"}], "move": "d6"}], "move": "e4"}], "move": "Bg7"}], "move": "Nc3"}], "move": "g6"}], "move": "c4"}], "move": "Nf6"}, {"count": 1, "win": 1, "games": [62], "draw": 0, "lose": 0, "children": [{"count": 1, "win": 1, "games": [62], "draw": 0, "lose": 0, "children": [{"count": 1, "win": 1, "games": [62], "draw": 0, "lose": 0, "children": [{"count": 1, "win": 1, "games": [62], "draw": 0, "lose": 0, "children": [], "move": "Qh5#"}], "move": "g5"}], "move": "e4"}], "move": "f6"}, {"count": 1, "win": 1, "games": [54], "draw": 0, "lose": 0, "children": [{"count": 1, "win": 1, "games": [54], "draw": 0, "lose": 0, "children": [{"count": 1, "win": 1, "games": [54], "draw": 0, "lose": 0, "children": [{"count": 1, "win": 1, "games": [54], "draw": 0, "lose": 0, "children": [{"count": 1, "win": 1, "games": [54], "draw": 0, "lose": 0, "children": [{"count": 1, "win": 1, "games": [54], "draw": 0, "lose": 0, "children": [{"count": 1, "win": 1, "games": [54], "draw": 0, "lose": 0, "children": [{"count": 1, "win": 1, "games": [54], "draw": 0, "lose": 0, "children": [{"count": 1, "win": 1, "games": [54], "draw": 0, "lose": 0, "children": [{"count": 1, "win": 1, "games": [54], "draw": 0, "lose": 0, "children": [], "move": "e4"}], "move": "b6"}], "move": "cxd5"}], "move": "exd5"}], "move": "Nc3"}], "move": "e6"}], "move": "c4"}], "move": "Nf6"}], "move": "d5"}], "move": "c5"}], "move": "d4"}]}, "black": {"children": [{"count": 18, "win": 12, "games": [32, 1, 33, 34, 64, 67, 11, 12, 48, 19, 21, 53, 55, 57, 26, 59, 29, 31], "draw": 0, "lose": 6, "children": [{"count": 18, "win": 12, "games": [32, 1, 33, 34, 64, 67, 11, 12, 48, 19, 21, 53, 55, 57, 26, 59, 29, 31], "draw": 0, "lose": 6, "children": [{"count": 4, "win": 3, "games": [64, 1, 11, 55], "draw": 0, "lose": 1, "children": [{"count": 4, "win": 3, "games": [64, 1, 11, 55], "draw": 0, "lose": 1, "children": [{"count": 1, "win": 0, "games": [1], "draw": 0, "lose": 1, "children": [{"count": 1, "win": 0, "games": [1], "draw": 0, "lose": 1, "children": [{"count": 1, "win": 0, "games": [1], "draw": 0, "lose": 1, "children": [{"count": 1, "win": 0, "games": [1], "draw": 0, "lose": 1, "children": [{"count": 1, "win": 0, "games": [1], "draw": 0, "lose": 1, "children": [{"count": 1, "win": 0, "games": [1], "draw": 0, "lose": 1, "children": [{"count": 1, "win": 0, "games": [1], "draw": 0, "lose": 1, "children": [], "move": "Qxd3"}], "move": "Bxd3"}], "move": "Bd3"}], "move": "e6"}], "move": "d4"}], "move": "Bf5"}], "move": "e5"}, {"count": 3, "win": 3, "games": [64, 11, 55], "draw": 0, "lose": 0, "children": [{"count": 3, "win": 3, "games": [64, 11, 55], "draw": 0, "lose": 0, "children": [{"count": 1, "win": 1, "games": [11], "draw": 0, "lose": 0, "children": [{"count": 1, "win": 1, "games": [11], "draw": 0, "lose": 0, "children": [{"count": 1, "win": 1, "games": [11], "draw": 0, "lose": 0, "children": [{"count": 1, "win": 1, "games": [11], "draw": 0, "lose": 0, "children": [{"count": 1, "win": 1, "games": [11], "draw": 0, "lose": 0, "children": [], "move": "b3"}], "move": "Nf6"}], "move": "c3"}], "move": "Nc6"}], "move": "Be2"}, {"count": 1, "win": 1, "games": [55], "draw": 0, "lose": 0, "children": [{"count": 1, "win": 1, "games": [55], "draw": 0, "lose": 0, "children": [{"count": 1, "win": 1, "games": [55], "draw": 0, "lose": 0, "children": [{"count": 1, "win": 1, "games": [55], "draw": 0, "lose": 0, "children": [{"count": 1, "win": 1, "games": [55], "draw": 0, "lose": 0, "children": [], "move": "d4"}], "move": "Nf6"}], "move": "Be2"}], "move": "Bg4"}], "move": "Nc3"}, {"count": 1, "win": 1, "games": [64], "draw": 0, "lose": 0, "children": [{"count": 1, "win": 1, "games": [64], "draw": 0, "lose": 0, "children": [{"count": 1, "win": 1, "games": [64], "draw": 0, "lose": 0, "children": [{"count": 1, "win": 1, "games": [64], "draw": 0, "lose": 0, "children": [{"count": 1, "win": 1, "games": [64], "draw": 0, "lose": 0, "children": [], "move": "Bb5"}], "move": "Bg4"}], "move": "d4"}], "move": "Nc6"}], "move": "c3"}], "move": "cxd5"}], "move": "exd5"}], "move": "d5"}], "move": "Nf3"}, {"count": 2, "win": 0, "games": [19, 29], "draw": 0, "lose": 2, "children": [{"count": 2, "win": 0, "games": [19, 29], "draw": 0, "lose": 2, "children": [{"count": 2, "win": 0, "games": [19, 29], "draw": 0, "lose": 2, "children": [{"count": 2, "win": 0, "games": [19, 29], "draw": 0, "lose": 2, "children": [{"count": 2, "win": 0, "games": [19, 29], "draw": 0, "lose": 2, "children": [{"count": 2, "win": 0, "games": [19, 29], "draw": 0, "lose": 2, "children": [{"count": 2, "win": 0, "games": [19, 29], "draw": 0, "lose": 2, "children": [{"count": 2, "win": 0, "games": [19, 29], "draw": 0, "lose": 2, "children": [{"count": 2, "win": 0, "games": [19, 29], "draw": 0, "lose": 2, "children": [], "move": "c3"}], "move": "c5"}], "move": "Nf3"}], "move": "e6"}], "move": "d4"}], "move": "Bf5"}], "move": "e5"}], "move": "d5"}], "move": "f4"}, {"count": 1, "win": 1, "games": [31], "draw": 0, "lose": 0, "children": [{"count": 1, "win": 1, "games": [31], "draw": 0, "lose": 0, "children": [{"count": 1, "win": 1, "games": [31], "draw": 0, "lose": 0, "children": [{"count": 1, "win": 1, "games": [31], "draw": 0, "lose": 0, "children": [{"count": 1, "win": 1, "games": [31], "draw": 0, "lose": 0, "children": [{"count": 1, "win": 1, "games": [31], "draw": 0, "lose": 0, "children": [{"count": 1, "win": 1, "games": [31], "draw": 0, "lose": 0, "children": [{"count": 1, "win": 1, "games": [31], "draw": 0, "lose": 0, "children": [{"count": 1, "win": 1, "games": [31], "draw": 0, "lose": 0, "children": [], "move": "Nxf3"}], "move": "Bxf3"}], "move": "Bf3"}], "move": "Bxg4"}], "move": "exd5"}], "move": "Nf6"}], "move": "Bg2"}], "move": "d5"}], "move": "g4"}, {"count": 1, "win": 0, "games": [53], "draw": 0, "lose": 1, "children": [{"count": 1, "win": 0, "games": [53], "draw": 0, "lose": 1, "children": [{"count": 1, "win": 0, "games": [53], "draw": 0, "lose": 1, "children": [{"count": 1, "win": 0, "games": [53], "draw": 0, "lose": 1, "children": [{"count": 1, "win": 0, "games": [53], "draw": 0, "lose": 1, "children": [{"count": 1, "win": 0, "games": [53], "draw": 0, "lose": 1, "children": [{"count": 1, "win": 0, "games": [53], "draw": 0, "lose": 1, "children": [{"count": 1, "win": 0, "games": [53], "draw": 0, "lose": 1, "children": [{"count": 1, "win": 0, "games": [53], "draw": 0, "lose": 1, "children": [], "move": "Bxc6+"}], "move": "a6"}], "move": "Bb5"}], "move": "Nc6"}], "move": "d4"}], "move": "cxd5"}], "move": "exd5"}], "move": "d5"}], "move": "Nc3"}, {"count": 9, "win": 7, "games": [32, 33, 34, 67, 12, 48, 21, 57, 59], "draw": 0, "lose": 2, "children": [{"count": 9, "win": 7, "games": [32, 33, 34, 67, 12, 48, 21, 57, 59], "draw": 0, "lose": 2, "children": [{"count": 1, "win": 1, "games": [33], "draw": 0, "lose": 0, "children": [{"count": 1, "win": 1, "games": [33], "draw": 0, "lose": 0, "children": [{"count": 1, "win": 1, "games": [33], "draw": 0, "lose": 0, "children": [{"count": 1, "win": 1, "games": [33], "draw": 0, "lose": 0, "children": [{"count": 1, "win": 1, "games": [33], "draw": 0, "lose": 0, "children": [{"count": 1, "win": 1, "games": [33], "draw": 0, "lose": 0, "children": [{"count": 1, "win": 1, "games": [33], "draw": 0, "lose": 0, "children": [], "move": "O-O"}], "move": "Nc6"}], "move": "Ne2"}], "move": "c5"}], "move": "Bd3"}], "move": "e6"}], "move": "f3"}, {"count": 5, "win": 3, "games": [32, 57, 59, 12, 21], "draw": 0, "lose": 2, "children": [{"count": 5, "win": 3, "games": [32, 57, 59, 12, 21], "draw": 0, "lose": 2, "children": [{"count": 2, "win": 2, "games": [32, 59], "draw": 0, "lose": 0, "children": [{"count": 2, "win": 2, "games": [32, 59], "draw": 0, "lose": 0, "children": [{"count": 1, "win": 1, "games": [32], "draw": 0, "lose": 0, "children": [{"count": 1, "win": 1, "games": [32], "draw": 0, "lose": 0, "children": [{"count": 1, "win": 1, "games": [32], "draw": 0, "lose": 0, "children": [], "move": "c3"}], "move": "c5"}], "move": "Be2"}, {"count": 1, "win": 1, "games": [59], "draw": 0, "lose": 0, "children": [{"count": 1, "win": 1, "games": [59], "draw": 0, "lose": 0, "children": [{"count": 1, "win": 1, "games": [59], "draw": 0, "lose": 0, "children": [], "move": "b3"}], "move": "c5"}], "move": "Nc3"}], "move": "e6"}], "move": "Nf3"}, {"count": 1, "win": 1, "games": [21], "draw": 0, "lose": 0, "children": [{"count": 1, "win": 1, "games": [21], "draw": 0, "lose": 0, "children": [{"count": 1, "win": 1, "games": [21], "draw": 0, "lose": 0, "children": [{"count": 1, "win": 1, "games": [21], "draw": 0, "lose": 0, "children": [{"count": 1, "win": 1, "games": [21], "draw": 0, "lose": 0, "children": [], "move": "Nf3"}], "move": "e6"}], "move": "Qxd3"}], "move": "Bxd3"}], "move": "Bd3"}, {"count": 2, "win": 0, "games": [57, 12], "draw": 0, "lose": 2, "children": [{"count": 2, "win": 0, "games": [57, 12], "draw": 0, "lose": 2, "children": [{"count": 2, "win": 0, "games": [57, 12], "draw": 0, "lose": 2, "children": [{"count": 2, "win": 0, "games": [57, 12], "draw": 0, "lose": 2, "children": [{"count": 2, "win": 0, "games": [57, 12], "draw": 0, "lose": 2, "children": [], "move": "Nf3"}], "move": "e6"}], "move": "f4"}], "move": "Bg6"}], "move": "g4"}], "move": "Bf5"}], "move": "e5"}, {"count": 3, "win": 3, "games": [48, 34, 67], "draw": 0, "lose": 0, "children": [{"count": 3, "win": 3, "games": [48, 34, 67], "draw": 0, "lose": 0, "children": [{"count": 1, "win": 1, "games": [34], "draw": 0, "lose": 0, "children": [{"count": 1, "win": 1, "games": [34], "draw": 0, "lose": 0, "children": [{"count": 1, "win": 1, "games": [34], "draw": 0, "lose": 0, "children": [{"count": 1, "win": 1, "games": [34], "draw": 0, "lose": 0, "children": [{"count": 1, "win": 1, "games": [34], "draw": 0, "lose": 0, "children": [], "move": "h3"}], "move": "Bg4"}], "move": "Bd3"}], "move": "Nf6"}], "move": "Nf3"}, {"count": 1, "win": 1, "games": [48], "draw": 0, "lose": 0, "children": [{"count": 1, "win": 1, "games": [48], "draw": 0, "lose": 0, "children": [{"count": 1, "win": 1, "games": [48], "draw": 0, "lose": 0, "children": [{"count": 1, "win": 1, "games": [48], "draw": 0, "lose": 0, "children": [{"count": 1, "win": 1, "games": [48], "draw": 0, "lose": 0, "children": [], "move": "Na3"}], "move": "bxc6"}], "move": "Bxc6+"}], "move": "Nc6"}], "move": "Bb5+"}, {"count": 1, "win": 1, "games": [67], "draw": 0, "lose": 0, "children": [{"count": 1, "win": 1, "games": [67], "draw": 0, "lose": 0, "children": [{"count": 1, "win": 1, "games": [67], "draw": 0, "lose": 0, "children": [{"count": 1, "win": 1, "games": [67], "draw": 0, "lose": 0, "children": [{"count": 1, "win": 1, "games": [67], "draw": 0, "lose": 0, "children": [], "move": "Nge2"}], "move": "Nf6"}], "move": "Qf3"}], "move": "Nc6"}], "move": "Nc3"}], "move": "cxd5"}], "move": "exd5"}], "move": "d5"}], "move": "d4"}, {"count": 1, "win": 1, "games": [26], "draw": 0, "lose": 0, "children": [{"count": 1, "win": 1, "games": [26], "draw": 0, "lose": 0, "children": [{"count": 1, "win": 1, "games": [26], "draw": 0, "lose": 0, "children": [{"count": 1, "win": 1, "games": [26], "draw": 0, "lose": 0, "children": [{"count": 1, "win": 1, "games": [26], "draw": 0, "lose": 0, "children": [{"count": 1, "win": 1, "games": [26], "draw": 0, "lose": 0, "children": [{"count": 1, "win": 1, "games": [26], "draw": 0, "lose": 0, "children": [{"count": 1, "win": 1, "games": [26], "draw": 0, "lose": 0, "children": [{"count": 1, "win": 1, "games": [26], "draw": 0, "lose": 0, "children": [], "move": "f4"}], "move": "e5"}], "move": "Bb5"}], "move": "Nc6"}], "move": "Bd3"}], "move": "cxd5"}], "move": "exd5"}], "move": "d5"}], "move": "Bc4"}], "move": "c6"}], "move": "e4"}, {"count": 1, "win": 1, "games": [42], "draw": 0, "lose": 0, "children": [{"count": 1, "win": 1, "games": [42], "draw": 0, "lose": 0, "children": [{"count": 1, "win": 1, "games": [42], "draw": 0, "lose": 0, "children": [{"count": 1, "win": 1, "games": [42], "draw": 0, "lose": 0, "children": [{"count": 1, "win": 1, "games": [42], "draw": 0, "lose": 0, "children": [{"count": 1, "win": 1, "games": [42], "draw": 0, "lose": 0, "children": [{"count": 1, "win": 1, "games": [42], "draw": 0, "lose": 0, "children": [{"count": 1, "win": 1, "games": [42], "draw": 0, "lose": 0, "children": [{"count": 1, "win": 1, "games": [42], "draw": 0, "lose": 0, "children": [{"count": 1, "win": 1, "games": [42], "draw": 0, "lose": 0, "children": [{"count": 1, "win": 1, "games": [42], "draw": 0, "lose": 0, "children": [], "move": "O-O"}], "move": "c5"}], "move": "Bg2"}], "move": "e6"}], "move": "g3"}], "move": "Bf5"}], "move": "c3"}], "move": "Nf6"}], "move": "d4"}], "move": "d5"}], "move": "Nf3"}, {"count": 1, "win": 1, "games": [14], "draw": 0, "lose": 0, "children": [{"count": 1, "win": 1, "games": [14], "draw": 0, "lose": 0, "children": [{"count": 1, "win": 1, "games": [14], "draw": 0, "lose": 0, "children": [{"count": 1, "win": 1, "games": [14], "draw": 0, "lose": 0, "children": [{"count": 1, "win": 1, "games": [14], "draw": 0, "lose": 0, "children": [{"count": 1, "win": 1, "games": [14], "draw": 0, "lose": 0, "children": [{"count": 1, "win": 1, "games": [14], "draw": 0, "lose": 0, "children": [{"count": 1, "win": 1, "games": [14], "draw": 0, "lose": 0, "children": [{"count": 1, "win": 1, "games": [14], "draw": 0, "lose": 0, "children": [{"count": 1, "win": 1, "games": [14], "draw": 0, "lose": 0, "children": [], "move": "Qf2#"}], "move": "c3"}], "move": "Qf6"}], "move": "Bg2"}], "move": "fxg3"}], "move": "g3"}], "move": "exf4"}], "move": "f4"}], "move": "e5"}], "move": "b3"}, {"count": 16, "win": 10, "games": [3, 36, 5, 37, 7, 39, 9, 41, 44, 15, 47, 18, 51, 22, 25, 63], "draw": 2, "lose": 4, "children": [{"count": 16, "win": 10, "games": [3, 36, 5, 37, 7, 39, 9, 41, 44, 15, 47, 18, 51, 22, 25, 63], "draw": 2, "lose": 4, "children": [{"count": 2, "win": 1, "games": [9, 7], "draw": 0, "lose": 1, "children": [{"count": 2, "win": 1, "games": [9, 7], "draw": 0, "lose": 1, "children": [{"count": 2, "win": 1, "games": [9, 7], "draw": 0, "lose": 1, "children": [{"count": 2, "win": 1, "games": [9, 7], "draw": 0, "lose": 1, "children": [{"count": 1, "win": 0, "games": [7], "draw": 0, "lose": 1, "children": [{"count": 1, "win": 0, "games": [7], "draw": 0, "lose": 1, "children": [{"count": 1, "win": 0, "games": [7], "draw": 0, "lose": 1, "children": [{"count": 1, "win": 0, "games": [7], "draw": 0, "lose": 1, "children": [{"count": 1, "win": 0, "games": [7], "draw": 0, "lose": 1, "children": [], "move": "Bxf6"}], "move": "Nc6"}], "move": "Bg5"}], "move": "c5"}], "move": "Nf3"}, {"count": 1, "win": 1, "games": [9], "draw": 0, "lose": 0, "children": [{"count": 1, "win": 1, "games": [9], "draw": 0, "lose": 0, "children": [{"count": 1, "win": 1, "games": [9], "draw": 0, "lose": 0, "children": [{"count": 1, "win": 1, "games": [9], "draw": 0, "lose": 0, "children": [{"count": 1, "win": 1, "games": [9], "draw": 0, "lose": 0, "children": [], "move": "Nb5"}], "move": "Bxc5"}], "move": "dxc5"}], "move": "c5"}], "move": "Nc3"}], "move": "Nf6"}], "move": "Bg2"}], "move": "e6"}], "move": "g3"}, {"count": 1, "win": 1, "games": [47], "draw": 0, "lose": 0, "children": [{"count": 1, "win": 1, "games": [47], "draw": 0, "lose": 0, "children": [{"count": 1, "win": 1, "games": [47], "draw": 0, "lose": 0, "children": [{"count": 1, "win": 1, "games": [47], "draw": 0, "lose": 0, "children": [{"count": 1, "win": 1, "games": [47], "draw": 0, "lose": 0, "children": [{"count": 1, "win": 1, "games": [47], "draw": 0, "lose": 0, "children": [{"count": 1, "win": 1, "games": [47], "draw": 0, "lose": 0, "children": [{"count": 1, "win": 1, "games": [47], "draw": 0, "lose": 0, "children": [{"count": 1, "win": 1, "games": [47], "draw": 0, "lose": 0, "children": [], "move": "Nc3"}], "move": "c6"}], "move": "Qd2"}], "move": "Na6"}], "move": "Nb5"}], "move": "e6"}], "move": "Bf4"}], "move": "Nf6"}], "move": "Nc3"}, {"count": 1, "win": 0, "games": [44], "draw": 1, "lose": 0, "children": [{"count": 1, "win": 0, "games": [44], "draw": 1, "lose": 0, "children": [{"count": 1, "win": 0, "games": [44], "draw": 1, "lose": 0, "children": [{"count": 1, "win": 0, "games": [44], "draw": 1, "lose": 0, "children": [{"count": 1, "win": 0, "games": [44], "draw": 1, "lose": 0, "children": [{"count": 1, "win": 0, "games": [44], "draw": 1, "lose": 0, "children": [{"count": 1, "win": 0, "games": [44], "draw": 1, "lose": 0, "children": [{"count": 1, "win": 0, "games": [44], "draw": 1, "lose": 0, "children": [{"count": 1, "win": 0, "games": [44], "draw": 1, "lose": 0, "children": [], "move": "Nf3"}], "move": "e6"}], "move": "e3"}], "move": "Nc6"}], "move": "c3"}], "move": "c5"}], "move": "h3"}], "move": "Nf6"}], "move": "Bf4"}, {"count": 2, "win": 1, "games": [5, 22], "draw": 0, "lose": 1, "children": [{"count": 2, "win": 1, "games": [5, 22], "draw": 0, "lose": 1, "children": [{"count": 1, "win": 1, "games": [22], "draw": 0, "lose": 0, "children": [{"count": 1, "win": 1, "games": [22], "draw": 0, "lose": 0, "children": [{"count": 1, "win": 1, "games": [22], "draw": 0, "lose": 0, "children": [{"count": 1, "win": 1, "games": [22], "draw": 0, "lose": 0, "children": [{"count": 1, "win": 1, "games": [22], "draw": 0, "lose": 0, "children": [{"count": 1, "win": 1, "games": [22], "draw": 0, "lose": 0, "children": [{"count": 1, "win": 1, "games": [22], "draw": 0, "lose": 0, "children": [], "move": "Be2"}], "move": "Nc6"}], "move": "e3"}], "move": "c5"}], "move": "Bd2"}], "move": "Nf6"}], "move": "Nc3"}, {"count": 1, "win": 0, "games": [5], "draw": 0, "lose": 1, "children": [{"count": 1, "win": 0, "games": [5], "draw": 0, "lose": 1, "children": [{"count": 1, "win": 0, "games": [5], "draw": 0, "lose": 1, "children": [{"count": 1, "win": 0, "games": [5], "draw": 0, "lose": 1, "children": [{"count": 1, "win": 0, "games": [5], "draw": 0, "lose": 1, "children": [{"count": 1, "win": 0, "games": [5], "draw": 0, "lose": 1, "children": [{"count": 1, "win": 0, "games": [5], "draw": 0, "lose": 1, "children": [], "move": "exd4"}], "move": "cxd4"}], "move": "e3"}], "move": "c5"}], "move": "Nc3"}], "move": "Nf6"}], "move": "Bf4"}], "move": "e6"}], "move": "Nf3"}, {"count": 6, "win": 4, "games": [36, 37, 39, 41, 18, 63], "draw": 0, "lose": 2, "children": [{"count": 6, "win": 4, "games": [36, 37, 39, 41, 18, 63], "draw": 0, "lose": 2, "children": [{"count": 1, "win": 1, "games": [37], "draw": 0, "lose": 0, "children": [{"count": 1, "win": 1, "games": [37], "draw": 0, "lose": 0, "children": [{"count": 1, "win": 1, "games": [37], "draw": 0, "lose": 0, "children": [{"count": 1, "win": 1, "games": [37], "draw": 0, "lose": 0, "children": [{"count": 1, "win": 1, "games": [37], "draw": 0, "lose": 0, "children": [{"count": 1, "win": 1, "games": [37], "draw": 0, "lose": 0, "children": [{"count": 1, "win": 1, "games": [37], "draw": 0, "lose": 0, "children": [], "move": "Nxd4"}], "move": "cxd4"}], "move": "e3"}], "move": "c5"}], "move": "Bg5"}], "move": "Nf6"}], "move": "Nf3"}, {"count": 4, "win": 2, "games": [63, 41, 36, 39], "draw": 0, "lose": 2, "children": [{"count": 4, "win": 2, "games": [63, 41, 36, 39], "draw": 0, "lose": 2, "children": [{"count": 2, "win": 1, "games": [36, 63], "draw": 0, "lose": 1, "children": [{"count": 2, "win": 1, "games": [36, 63], "draw": 0, "lose": 1, "children": [{"count": 1, "win": 0, "games": [36], "draw": 0, "lose": 1, "children": [{"count": 1, "win": 0, "games": [36], "draw": 0, "lose": 1, "children": [{"count": 1, "win": 0, "games": [36], "draw": 0, "lose": 1, "children": [], "move": "e4"}], "move": "Nxd5"}], "move": "cxd5"}, {"count": 1, "win": 1, "games": [63], "draw": 0, "lose": 0, "children": [{"count": 1, "win": 1, "games": [63], "draw": 0, "lose": 0, "children": [{"count": 1, "win": 1, "games": [63], "draw": 0, "lose": 0, "children": [], "move": "Nxd4"}], "move": "cxd4"}], "move": "Bg5"}], "move": "c5"}], "move": "Nf3"}, {"count": 2, "win": 1, "games": [41, 39], "draw": 0, "lose": 1, "children": [{"count": 2, "win": 1, "games": [41, 39], "draw": 0, "lose": 1, "children": [{"count": 1, "win": 0, "games": [41], "draw": 0, "lose": 1, "children": [{"count": 1, "win": 0, "games": [41], "draw": 0, "lose": 1, "children": [{"count": 1, "win": 0, "games": [41], "draw": 0, "lose": 1, "children": [], "move": "cxd5"}], "move": "Qxf6"}], "move": "Bxf6"}, {"count": 1, "win": 1, "games": [39], "draw": 0, "lose": 0, "children": [{"count": 1, "win": 1, "games": [39], "draw": 0, "lose": 0, "children": [{"count": 1, "win": 1, "games": [39], "draw": 0, "lose": 0, "children": [], "move": "cxd5"}], "move": "Bxc5"}], "move": "dxc5"}], "move": "c5"}], "move": "Bg5"}], "move": "Nf6"}], "move": "Nc3"}, {"count": 1, "win": 1, "games": [18], "draw": 0, "lose": 0, "children": [{"count": 1, "win": 1, "games": [18], "draw": 0, "lose": 0, "children": [{"count": 1, "win": 1, "games": [18], "draw": 0, "lose": 0, "children": [{"count": 1, "win": 1, "games": [18], "draw": 0, "lose": 0, "children": [{"count": 1, "win": 1, "games": [18], "draw": 0, "lose": 0, "children": [{"count": 1, "win": 1, "games": [18], "draw": 0, "lose": 0, "children": [{"count": 1, "win": 1, "games": [18], "draw": 0, "lose": 0, "children": [], "move": "e4"}], "move": "c5"}], "move": "Nc3"}], "move": "exd5"}], "move": "cxd5"}], "move": "Nf6"}], "move": "a3"}], "move": "e6"}], "move": "c4"}, {"count": 1, "win": 1, "games": [3], "draw": 0, "lose": 0, "children": [{"count": 1, "win": 1, "games": [3], "draw": 0, "lose": 0, "children": [{"count": 1, "win": 1, "games": [3], "draw": 0, "lose": 0, "children": [{"count": 1, "win": 1, "games": [3], "draw": 0, "lose": 0, "children": [{"count": 1, "win": 1, "games": [3], "draw": 0, "lose": 0, "children": [{"count": 1, "win": 1, "games": [3], "draw": 0, "lose": 0, "children": [{"count": 1, "win": 1, "games": [3], "draw": 0, "lose": 0, "children": [{"count": 1, "win": 1, "games": [3], "draw": 0, "lose": 0, "children": [{"count": 1, "win": 1, "games": [3], "draw": 0, "lose": 0, "children": [], "move": "a3"}], "move": "Nc6"}], "move": "e3"}], "move": "c5"}], "move": "h4"}], "move": "Nf6"}], "move": "Nf3"}], "move": "e6"}], "move": "c3"}, {"count": 3, "win": 2, "games": [25, 51, 15], "draw": 1, "lose": 0, "children": [{"count": 3, "win": 2, "games": [25, 51, 15], "draw": 1, "lose": 0, "children": [{"count": 2, "win": 1, "games": [25, 51], "draw": 1, "lose": 0, "children": [{"count": 2, "win": 1, "games": [25, 51], "draw": 1, "lose": 0, "children": [{"count": 1, "win": 1, "games": [51], "draw": 0, "lose": 0, "children": [{"count": 1, "win": 1, "games": [51], "draw": 0, "lose": 0, "children": [{"count": 1, "win": 1, "games": [51], "draw": 0, "lose": 0, "children": [{"count": 1, "win": 1, "games": [51], "draw": 0, "lose": 0, "children": [{"count": 1, "win": 1, "games": [51], "draw": 0, "lose": 0, "children": [], "move": "Nxd4"}], "move": "cxd4"}], "move": "b3"}], "move": "c5"}], "move": "c4"}, {"count": 1, "win": 0, "games": [25], "draw": 1, "lose": 0, "children": [{"count": 1, "win": 0, "games": [25], "draw": 1, "lose": 0, "children": [{"count": 1, "win": 0, "games": [25], "draw": 1, "lose": 0, "children": [{"count": 1, "win": 0, "games": [25], "draw": 1, "lose": 0, "children": [{"count": 1, "win": 0, "games": [25], "draw": 1, "lose": 0, "children": [], "move": "Bb5"}], "move": "Nc6"}], "move": "Nc3"}], "move": "c5"}], "move": "Ne5"}], "move": "Nf6"}], "move": "Nf3"}, {"count": 1, "win": 1, "games": [15], "draw": 0, "lose": 0, "children": [{"count": 1, "win": 1, "games": [15], "draw": 0, "lose": 0, "children": [{"count": 1, "win": 1, "games": [15], "draw": 0, "lose": 0, "children": [{"count": 1, "win": 1, "games": [15], "draw": 0, "lose": 0, "children": [{"count": 1, "win": 1, "games": [15], "draw": 0, "lose": 0, "children": [{"count": 1, "win": 1, "games": [15], "draw": 0, "lose": 0, "children": [{"count": 1, "win": 1, "games": [15], "draw": 0, "lose": 0, "children": [], "move": "f4"}], "move": "Nc6"}], "move": "c3"}], "move": "c5"}], "move": "Nd2"}], "move": "Nf6"}], "move": "Bd3"}], "move": "e6"}], "move": "e3"}], "move": "d5"}], "move": "d4"}]}, "games": [{"speed": "classical", "clock": {"increment": 5, "initial": 300, "totalTime": 500}, "moves": "d4 d5 c4 e6 Nc3 Nf6 Bg5 Bb4 Nf3 O-O e3 Nbd7 a3 Be7 Bxf6 Nxf6 b4 a6 Be2 b6 Ne5 Bb7 Qa4 b5 cxb5 axb5 Qxb5 Ba6 Qc6 Bxe2 Nxe2 Ne4 O-O Bd6 Nd3 Qh4 g3 Qh5 Nef4 Qf3 Ne5 Ng5 Nxf3 Nxf3+ Kg2 Nd2 Rfc1 Nb3 Rab1 Nxc1 Rxc1 Rxa3 Rc3 Ra2 b5 Rb8 Rc2 Ra7 Rb2 Rb6 Qe8+ Bf8 Nd3 Rab7 Nc5 Rb8 Nd7 Rxe8 Nxb6 cxb6 Rc2 Rb8 Rc6 Bb4 f3 Ba5 e4 dxe4 fxe4 Rd8 e5 g6 Rd6 Rc8 Kh3 Rc4 d5 exd5 Rxd5 Re4 g4 Kg7 Kg3 g5 h4 h6 h5 Be1+ Kf3 Rf4+ Ke2 Ba5 Ke3 Rxg4 Rd6 Rb4 e6 fxe6 Rxe6 Rxb5 Re7+ Kf6 Rh7 g4 Rxh6+ Kg5 Rh8 Re5+ Kf2 Kh4 h6 Rh5 Kg2 g3 h7 Rh6 Rg8 Rxh7 Rxg3 Rf7 Rh3+ Kg5 Rg3+ Kh6 Rh3+ Kg7 Rg3+ Kf8 Re3 Rb7 Ra3 Bd2 Kf3 b5 Ke2 Bh6 Ra8+ Ke7 Rh8 Bg7 Rh7 Kf6 Kd3 b4 Kc2 b3+ Kb1 Kg6 Rh2 Be5 Rg2+ Kf6 Rf2+ Ke6 Rd2 Rh7 Rd1 Rh2 Rc1 Kd5 Rd1+ Bd4 Rc1 Be3 Rd1+ Kc4 Ka1 Kc3 Rb1 Bc5 Rc1+ Kb4 Rb1 Bd4+ Rb2 Rxb2", "url": "http://lichess.org/B9YNaCKT/black", "rated": true, "id": "B9YNaCKT", "status": "stalemate", "variant": "standard", "perf": "classical", "turns": 186, "players": {"white": {"userId": "whiznl", "ratingDiff": 0, "rating": 1805}, "black": {"userId": "mainu", "ratingDiff": 0, "rating": 1806}}, "timestamp": 1462220841152}, {"speed": "classical", "clock": {"increment": 5, "initial": 300, "totalTime": 500}, "moves": "e4 c6 Nf3 d5 e5 Bf5 d4 e6 Bd3 Bxd3 Qxd3 c5 c3 Nc6 Qb5 Qb6 Qxb6 axb6 O-O cxd4 cxd4 Nge7 Nc3 Na7 a4 Nf5 b3 Bb4 Bb2 O-O h3 Rfc8 Ne2 b5 Rfc1 Rc6 axb5 Rxc1+ Bxc1 b6 Ra6", "url": "http://lichess.org/KfnLygUV/white", "rated": true, "id": "KfnLygUV", "status": "outoftime", "winner": "white", "variant": "standard", "perf": "classical", "turns": 41, "players": {"white": {"userId": "yesindeed", "ratingDiff": 11, "rating": 1820, "analysis": {"blunder": 1, "mistake": 0, "inaccuracy": 0}}, "black": {"userId": "whiznl", "ratingDiff": -11, "rating": 1816, "analysis": {"blunder": 2, "mistake": 0, "inaccuracy": 0}}}, "timestamp": 1462220125117}, {"speed": "classical", "clock": {"increment": 5, "initial": 300, "totalTime": 500}, "moves": "d4 d5 c4 dxc4 e3 e5 Bxc4 Bb4+ Nc3 Nc6 Nf3 Bg4 a3 Bxc3+ bxc3 exd4 cxd4 Nf6 O-O O-O h3 Bh5 Be2 Ne4 Bb2 Na5 Qd3 Re8 Nd2 Bg6 Nxe4 Bxe4 Qc3 Qg5 f3 Bf5 e4 Bxh3 Rf2 Nc6 d5 Ne5 f4 Nf3+ Qxf3 Qg4 Qxg4 Bxg4 Bxg4 Rxe4 g3 g5 Kf1 Rae8 Bd7 R8e7 Bg4 Rd7 Rd1 Rd8 Bf6 Rde8 Bxg5 Kh8 Bf6+ Kg8 Bd7 Rf8 Re1 Rxe1+ Kxe1 h5 Be7 Rb8 f5 Kh7 Rf4 Kh6 Rh4 b5 Ke2 a5 Rh1", "url": "http://lichess.org/68XKN9Wb/white", "rated": true, "id": "68XKN9Wb", "status": "outoftime", "winner": "white", "variant": "standard", "perf": "classical", "turns": 83, "players": {"white": {"userId": "whiznl", "ratingDiff": 6, "rating": 1810, "analysis": {"blunder": 0, "mistake": 4, "inaccuracy": 7}}, "black": {"userId": "santanajj", "ratingDiff": -5, "rating": 1627, "analysis": {"blunder": 1, "mistake": 9, "inaccuracy": 3}}}, "timestamp": 1462050127515}, {"speed": "classical", "clock": {"increment": 5, "initial": 300, "totalTime": 500}, "moves": "d4 d5 c3 e6 Nf3 Nf6 h4 c5 e3 Nc6 a3 a6 b4 b6 b5 axb5 Bxb5 Bd7 Ne5 Qc7 Bxc6 Bxc6 g4 Bd6 g5 Nd7 Qf3 Nxe5 dxe5 Bxe5 h5 f5 gxf6 gxf6 h6 O-O-O a4 f5 Rg1 Rhg8 Rxg8 Rxg8 Bd2 d4 Qe2 Rg1+ Qf1 Rxf1+ Kxf1 dxe3 Bxe3 Qd6 Ke2 f4 Bd2 f3+ Ke1 Bf4 a5 Bxd2+ Nxd2 bxa5 Rxa5 Qd3 Rxc5 Qe2#", "url": "http://lichess.org/zfC2Q8KB/black", "rated": true, "id": "zfC2Q8KB", "status": "mate", "winner": "black", "variant": "standard", "perf": "classical", "turns": 66, "players": {"white": {"userId": "mikhail_l", "ratingDiff": -7, "rating": 1720, "analysis": {"blunder": 2, "mistake": 5, "inaccuracy": 5}}, "black": {"userId": "whiznl", "ratingDiff": 10, "rating": 1800, "analysis": {"blunder": 1, "mistake": 2, "inaccuracy": 3}}}, "timestamp": 1462044511791}, {"speed": "classical", "clock": {"increment": 5, "initial": 300, "totalTime": 500}, "moves": "d4 e6 c4 Ne7 e4 b6 Nc3 Bb7 Nf3 Ng6 g3 Bb4 Bd3 d6 a3 Bxc3+ bxc3 Nd7 O-O h5 a4 h4 Bg5 f6 Nxh4 Nxh4 Bxh4 g5 Qg4 Qe7 e5 dxe5 Bg6+ Kd8 dxe5 Nxe5 Qd4+ Kc8 Bxg5 Nf3+", "url": "http://lichess.org/Oh0tbO6s/white", "rated": true, "id": "Oh0tbO6s", "status": "resign", "winner": "black", "variant": "standard", "perf": "classical", "turns": 40, "players": {"white": {"userId": "whiznl", "ratingDiff": -13, "rating": 1813}, "black": {"userId": "mbaglole", "ratingDiff": 13, "rating": 1767}}, "timestamp": 1462038970893}, {"speed": "classical", "clock": {"increment": 5, "initial": 300, "totalTime": 500}, "moves": "d4 d5 Nf3 e6 Bf4 Nf6 Nc3 c5 e3 cxd4 exd4 Nc6 Nb5 Qa5+ c3 e5 Nxe5 Be7 Nxc6 bxc6 Nc7+ Kd8 Nxa8 Ne8 b4 Qa3 Qb3 Bxb4 cxb4", "url": "http://lichess.org/CLglqvWH/black", "rated": true, "id": "CLglqvWH", "status": "resign", "winner": "white", "variant": "standard", "perf": "classical", "turns": 29, "players": {"white": {"userId": "kaspaperov", "ratingDiff": 11, "rating": 1820}, "black": {"userId": "whiznl", "ratingDiff": -11, "rating": 1824}}, "timestamp": 1462021794714}, {"speed": "classical", "clock": {"increment": 5, "initial": 300, "totalTime": 500}, "moves": "d4 Nf6 c4 g6 Nc3 Bg7 e4 d6 Nf3 e5 dxe5 dxe5 Qxd8+ Kxd8", "url": "http://lichess.org/wUULiQIn/black", "rated": true, "id": "wUULiQIn", "status": "resign", "winner": "white", "variant": "standard", "perf": "classical", "turns": 14, "players": {"white": {"userId": "whiznl", "ratingDiff": 16, "rating": 1808, "analysis": {"blunder": 0, "mistake": 0, "inaccuracy": 0}}, "black": {"userId": "bektas", "ratingDiff": -14, "rating": 1924, "analysis": {"blunder": 0, "mistake": 0, "inaccuracy": 1}}}, "timestamp": 1462021171563}, {"speed": "classical", "clock": {"increment": 5, "initial": 300, "totalTime": 500}, "moves": "d4 d5 g3 e6 Bg2 Nf6 Nf3 c5 Bg5 Nc6 Bxf6 Qxf6 c3 b6 O-O Ba6 Re1 Bd6 e4 dxe4 Rxe4 O-O d5 Nd8 dxe6 Bb7 Re3 Bxf3 Bxf3 fxe6 Bxa8 Bxg3 Rf3 Bxh2+ Kf1 Qg6 Rxf8+ Kxf8 Qxd8+ Kf7 Bg2 Qc2 Na3 Qxb2 Rd1 Qxa3 Rd7+ Kg6 Be4+ Kh5 Bf3+ Kg6 Qe8+ Kf5 Qh5+ Kf6 Rf7#", "url": "http://lichess.org/rmBSyMCH/black", "rated": true, "id": "rmBSyMCH", "status": "mate", "winner": "white", "variant": "standard", "perf": "classical", "turns": 57, "players": {"white": {"userId": "marecuic13", "ratingDiff": 13, "rating": 1792, "analysis": {"blunder": 3, "mistake": 1, "inaccuracy": 1}}, "black": {"userId": "whiznl", "ratingDiff": -12, "rating": 1820, "analysis": {"blunder": 3, "mistake": 7, "inaccuracy": 2}}}, "timestamp": 1461497563128}, {"speed": "classical", "clock": {"increment": 5, "initial": 300, "totalTime": 500}, "moves": "d4 d5 c4 e5 dxe5 d4 Nf3 c5 h3 Nc6 e3 Bf5 Qa4 Qa5+ Qxa5 Nxa5 b3 dxe3 Bxe3 Bxb1 Rxb1 Ne7 Bxc5 Nec6 Bxf8 Rxf8 Be2 Rd8 O-O Nd4 Nxd4 Rxd4 Rfd1 Nc6 Rxd4 Nxd4 Bg4 Ke7 Rd1 Ne6 h4 g6 g3 h5 Bh3 Rd8 Rxd8 Nxd8 f4 Nc6 g4 Nd4 Kf2 Nc2 f5 Nb4 fxg6 fxg6 gxh5 Nd3+ Ke3 Nxe5 Kf4 Nd3+ Kg5 gxh5 Kxh5 Nf4+ Kg4 Nd3 Kg5 Kf7 Bc8 b6 h5 Ne5 Bf5 Kg7 h6+ Kh8 h7 Nf7+ Kg6 Nd6 Be6 Ne8 Bf5 a5 Kf7 Nd6+ Ke6 Nb7 Kd5", "url": "http://lichess.org/p5wuy8s6/black", "rated": true, "id": "p5wuy8s6", "status": "timeout", "winner": "white", "variant": "standard", "perf": "classical", "turns": 93, "players": {"white": {"userId": "whiznl", "ratingDiff": 15, "rating": 1805, "analysis": {"blunder": 0, "mistake": 6, "inaccuracy": 3}}, "black": {"userId": "acalojda2", "ratingDiff": -12, "rating": 1877, "analysis": {"blunder": 1, "mistake": 9, "inaccuracy": 6}}}, "timestamp": 1461271175352}, {"speed": "classical", "clock": {"increment": 5, "initial": 300, "totalTime": 500}, "moves": "d4 d5 g3 e6 Bg2 Nf6 Nc3 c5 dxc5 Bxc5 Nb5 a6 Nd4 Nc6 Be3 Nxd4 Bxd4 Qc7", "url": "http://lichess.org/ciFUy3Ty/black", "rated": true, "id": "ciFUy3Ty", "status": "outoftime", "winner": "black", "variant": "standard", "perf": "classical", "turns": 18, "players": {"white": {"userId": "goodis9", "ratingDiff": -9, "rating": 1551}, "black": {"userId": "whiznl", "ratingDiff": 5, "rating": 1800}}, "timestamp": 1461270746057}, {"speed": "classical", "clock": {"increment": 5, "initial": 300, "totalTime": 500}, "moves": "d4 d5 c4 e5 dxe5 d4 Nf3 c5 e3 Bg4 g3 Nc6 Bg2 Nxe5 b3 dxe3 Qxd8+ Rxd8 Nxe5 Rd1#", "url": "http://lichess.org/IvWdv8PF/black", "rated": true, "id": "IvWdv8PF", "status": "mate", "winner": "black", "variant": "standard", "perf": "classical", "turns": 20, "players": {"white": {"userId": "whiznl", "ratingDiff": -10, "rating": 1810}, "black": {"userId": "acalojda2", "ratingDiff": 9, "rating": 1860}}, "timestamp": 1461270543746}, {"speed": "classical", "clock": {"increment": 5, "initial": 300, "totalTime": 500}, "moves": "e4 c6 Nf3 d5 exd5 cxd5 Be2 Nc6 c3 Nf6 b3 Bg4 Ng5 Bxe2 Qxe2 h6 Nf3 e6 O-O Bd6 d4 Qc7 Ba3 Bxa3 Nxa3 a6 c4 Nb4 c5 b6 Rac1 O-O Qd2 Nd7 Qxb4 a5 cxb6 Qxb6 Qd2 Qb4 Qxb4 axb4 Nc2 Rxa2 Nxb4 Rb2 Rb1 Rxb1 Rxb1 Rb8 Nc6 Rb6 Ne7+ Kf8 Nc8 Ra6 Ne5 Ke8 b4 Kd8 b5 Ra8 Nxd7 Rxc8 Nb6 Rb8 Na4 Kd7 b6 Kc6 Rc1+ Kb5 Nc3+ Kxb6 Rb1+ Kc7 Nb5+ Kd8 f3 Kd7 Kf2 Kc6 Na7+ Kc7 Rxb8 Kxb8 Nb5 Kb7 Nc3 Kc6 h4 f6 g3 e5 Ke3 exd4+ Kxd4 Kd6 Nxd5 Ke6 f4 g5 hxg5 hxg5 fxg5 fxg5 Ne3 Kf6 Ke4 Kg6 Ng4 Kh5 Kf3 Kg6 Ne5+ Kf5 Nf7 Kg6 Nxg5 Kxg5 g4 Kg6", "url": "http://lichess.org/XcbMz2aZ/black", "rated": true, "id": "XcbMz2aZ", "status": "timeout", "winner": "black", "variant": "standard", "perf": "classical", "turns": 122, "players": {"white": {"userId": "nnaassaa", "ratingDiff": -6, "rating": 1637, "analysis": {"blunder": 1, "mistake": 5, "inaccuracy": 8}}, "black": {"userId": "whiznl", "ratingDiff": 8, "rating": 1802, "analysis": {"blunder": 3, "mistake": 5, "inaccuracy": 4}}}, "timestamp": 1461265322368}, {"speed": "classical", "clock": {"increment": 5, "initial": 300, "totalTime": 500}, "moves": "e4 c6 d4 d5 e5 Bf5 g4 Bg6 f4 e6 Nf3 c5 Be3 cxd4 Bxd4 Nc6 Bc3 Be7 g5 h6 h4 Be4 Bd3 hxg5 fxg5 Bxg5 Bxe4 dxe4 Nxg5 Rxh4 Qxd8+", "url": "http://lichess.org/wthPvhB5/black", "rated": true, "id": "wthPvhB5", "status": "resign", "winner": "white", "variant": "standard", "perf": "classical", "turns": 31, "players": {"white": {"userId": "propal", "ratingDiff": 13, "rating": 1764, "analysis": {"blunder": 0, "mistake": 3, "inaccuracy": 0}}, "black": {"userId": "whiznl", "ratingDiff": -14, "rating": 1816, "analysis": {"blunder": 1, "mistake": 1, "inaccuracy": 1}}}, "timestamp": 1461264645171}, {"speed": "classical", "clock": {"increment": 5, "initial": 300, "totalTime": 500}, "moves": "d4 b6 c4 Bb7 Nc3 c5 d5 e6 e4 Bd6 Nf3 exd5 cxd5 Nf6 e5 Bxe5 Nxe5 d6 Bb5+ Kf8 Nf3 a6 Ba4 b5 Bc2 b4 Ne4 Bxd5 Nxf6 gxf6 Qxd5 Ra7 Bf4 Qe7+ Qe4 Qe6 Qxe6 fxe6 Bh6+ Kf7 O-O Nd7 Rad1 Ne5 Rxd6 Ng4 Bf4 e5 h3 Ke7 Rfd1 Kf8 Bd2 e4 Rd8+ Kg7 Bh6+ Nxh6 Bxe4 f5 Rxh8 Kxh8 Bc6 Rc7 Bd5 Rd7 Bb3 Re7 Re1 Rg7 Re8+ Ng8 Bxg8 Rxg8 Rxg8+ Kxg8 Ne5 a5 g4 a4 gxf5 a3 b3 c4 bxc4 b3 Nf3 bxa2 f6 Kf7 c5 a1=Q+ Kg2 Qxf6 h4 a2 Ng5+ Kf8 Nxh7+ Kg7 Nxf6 Kxf6 c6 a1=Q c7 Qc3 h5 Qxc7 h6 Qh7", "url": "http://lichess.org/37tjxJ1Z/white", "rated": true, "id": "37tjxJ1Z", "status": "resign", "winner": "black", "variant": "standard", "perf": "classical", "turns": 110, "players": {"white": {"userId": "whiznl", "ratingDiff": -20, "rating": 1836}, "black": {"provisional": true, "userId": "lsldv98", "ratingDiff": 125, "rating": 1429}}, "timestamp": 1461263612003}, {"speed": "classical", "clock": {"increment": 5, "initial": 300, "totalTime": 500}, "moves": "b3 e5 f4 exf4 g3 fxg3 Bg2 Qf6 c3 Qf2#", "url": "http://lichess.org/lcDyRpcT/black", "rated": true, "id": "lcDyRpcT", "status": "mate", "winner": "black", "variant": "standard", "perf": "classical", "turns": 10, "players": {"white": {"provisional": true, "userId": "lsldv98", "ratingDiff": -13, "rating": 1442}, "black": {"userId": "whiznl", "ratingDiff": 3, "rating": 1833}}, "timestamp": 1461263495929}, {"speed": "classical", "clock": {"increment": 5, "initial": 300, "totalTime": 500}, "moves": "d4 d5 e3 e6 Bd3 Nf6 Nd2 c5 c3 Nc6 f4 a6 Ngf3 c4 Bc2 b5 O-O Bd6 Ne5 Ne7 g4 h5 Qf3 O-O g5 Ng4 h3 Bxe5 fxe5 Nxe3 Qxe3 Nf5 Bxf5 exf5 b3 f4 Qxf4 Bxh3 Rf3 Bg4 Rf2 Ra7 Ba3 Re8 Bd6 Re6 Qxf7+ Rxf7", "url": "http://lichess.org/QlRExmSQ/white", "rated": true, "id": "QlRExmSQ", "status": "timeout", "winner": "black", "variant": "standard", "perf": "classical", "turns": 48, "players": {"white": {"userId": "eisaaa", "ratingDiff": -14, "rating": 1948, "analysis": {"blunder": 1, "mistake": 1, "inaccuracy": 2}}, "black": {"userId": "whiznl", "ratingDiff": 18, "rating": 1815, "analysis": {"blunder": 1, "mistake": 1, "inaccuracy": 3}}}, "timestamp": 1460835341969}, {"speed": "classical", "clock": {"increment": 5, "initial": 300, "totalTime": 500}, "moves": "d4 d5 c4 dxc4 e3 e6 Nc3 Bd7 Bxc4 a6 a4 Nc6 b3 Nf6 Nf3 Bb4 Qc2 Be7 O-O Nb4 Qd2 a5 Ba3 Nc6 Bxe7 Qxe7 Bb5 Nd5 Bxc6 bxc6 Ne5 f6 Nxd7 Qxd7 Ne4 h6 Nc5 Qe7 Qd3 Rb8 Qg6+ Kf8 Rab1 e5 Rfe1 Re8 Rbc1 Nb4 Rc3 Nd5 Rc4 exd4 e4 Nb6 Rc2 Nd7 Nxd7+ Qxd7 Rec1 d3 Rxc6 d2 Rd1 Qxc6 Rxd2 Qc1+", "id": "ChNg8TYH", "rated": true, "url": "http://lichess.org/ChNg8TYH/white", "status": "resign", "timestamp": 1460476174409, "winner": "black", "variant": "standard", "perf": "classical", "turns": 66, "players": {"white": {"userId": "whiznl", "ratingDiff": -15, "rating": 1830}, "black": {"userId": "nassar", "ratingDiff": 15, "rating": 1743}}}, {"speed": "classical", "clock": {"increment": 5, "initial": 300, "totalTime": 500}, "moves": "d4 h6 c4 e6 Nc3 c6 Nf3 a6 e4 b5 b3 b4 Na4 d5 Bd3 Nf6 e5 Nfd7 O-O f5 c5 Be7 a3 a5 axb4 axb4 Bd2 Ba6 Bxa6 Nxa6 Qe1 Rb8 Nb6 Nxb6 Rxa6 Nd7 Bxb4 Qc8 Ra4 O-O Qe2 Rb5 Nd2 g6 Nb1 Bg5 Na3 Rb7 g3 Nb8 f4 Bd8 Qd2 Qd7 h3 h5 Ra1 Bc7 Qc3 Rc8 Ba5 Bd8 Bxd8 Qxd8 Nc2 Qc7 Rb4 Rb5 Rxb5 cxb5 b4 Qc6 Qa3 Nd7 Qa6 Qxa6 Rxa6 Kf7 Na3 Nb8 Ra5 Nc6 Rxb5 Nxd4 Rb7+ Kf8 Nb5 Nxb5 Rxb5 Ra8 c6 Ke8 Rb7 Rc8 b5 Kd8 Rd7+ Ke8 Rd6 Ke7 b6 Rxc6 Rxc6 Kd7 Rc7+ Kd8 Rc2 Kd7 b7 Kd8 b8=Q+ Ke7 Rc7#", "id": "rkG0nO1F", "rated": true, "url": "http://lichess.org/rkG0nO1F/white", "status": "mate", "timestamp": 1460296530346, "winner": "white", "variant": "standard", "perf": "classical", "turns": 113, "players": {"white": {"userId": "whiznl", "ratingDiff": 4, "rating": 1826}, "black": {"userId": "rudzanimat", "ratingDiff": -3, "rating": 1523}}}, {"speed": "classical", "clock": {"increment": 5, "initial": 300, "totalTime": 500}, "moves": "d4 d5 c4 e6 a3 Nf6 cxd5 exd5 Nc3 c5 e4 Nxe4 Nxe4 dxe4 d5 a6 Bf4 b5 h3 Bb7 d6 g5 Be5 Rg8 Qd2 f6 Bg3 f5 O-O-O f4 Bh2 Rg6 g3 Rxd6 Qe2 Rxd1+ Qxd1 Qxd1+ Kxd1 f3 g4 Nc6 Bg3 Nd4 h4 gxh4 Bxh4 h6 Bf6 Ne6 Nh3 Be7 Be5 Rd8+ Kc1 Rd5 Bg3 Bg5+ Kc2 Rd2+ Kc3 Nd4 Nf4 Bxf4 Bxf4 Rxf2 Bh3 Rc2#", "id": "LQRShlhM", "rated": true, "url": "http://lichess.org/LQRShlhM/black", "status": "mate", "timestamp": 1460290701222, "winner": "black", "variant": "standard", "perf": "classical", "turns": 68, "players": {"white": {"userId": "deboisky", "ratingDiff": -9, "rating": 1793, "analysis": {"blunder": 4, "mistake": 3, "inaccuracy": 7}}, "black": {"userId": "whiznl", "ratingDiff": 13, "rating": 1813, "analysis": {"blunder": 2, "mistake": 4, "inaccuracy": 4}}}}, {"speed": "classical", "clock": {"increment": 5, "initial": 300, "totalTime": 500}, "moves": "e4 c6 f4 d5 e5 Bf5 d4 e6 Nf3 c5 c3 Nc6 Bd3 Bxd3 Qxd3 Nge7 O-O Nf5 Be3 Nxe3 Qxe3 Qb6 Rf2 cxd4 cxd4 Be7 Ng5 Qxd4 Qxd4 Nxd4 Nc3 a6 Rd1 Nf5 Nf3 Ne3 Rc1 Bb4 Re2 Bxc3 Rxc3 Nc4 b3 Na3 Rc7 Rb8 Re1 O-O Ng5 Nb5 Rcc1 Rbc8 Nf3 Rxc1 Rxc1 h6 Kf2 f6 Ke3 fxe5 Nxe5 Kh7 g3 Nd6 Rc7 Nf5+ Kd3 Nd6 Rd7 Nf5 Rxb7 Rc8 Rb6 a5 Rxe6 Rc1 Ra6 Rh1 Nf3 Rf1 Ke2 Rxf3 Kxf3 Nd6 Rxd6", "id": "hfc8QeD3", "rated": true, "url": "http://lichess.org/hfc8QeD3/black", "status": "resign", "timestamp": 1460288925965, "winner": "white", "variant": "standard", "perf": "classical", "turns": 85, "players": {"white": {"userId": "whateveryaar", "ratingDiff": 15, "rating": 1747}, "black": {"userId": "whiznl", "ratingDiff": -15, "rating": 1828}}}, {"speed": "classical", "clock": {"increment": 5, "initial": 300, "totalTime": 500}, "moves": "d4 d5 c4 e6 Nc3 Nf6 Nf3 c6 e3 Nbd7 a3 Be7 b4 dxc4 Bxc4 Nb6 Bb3 O-O O-O Bd7 a4 a5 b5 cxb5 Nxb5 Bxb5 axb5 a4 Bxa4 Nxa4 Rxa4 Qb6 Qb3 Nd5 Ba3 Bxa3 Qxa3 Rxa4 Qxa4 Nc3 Qc4 Nd5 Ne5 Qd6 Rc1 g6 g3 Rd8 e4 Nf6 f3 Qxd4+ Qxd4 Rxd4 b6 Rb4 Rc8+ Kg7 Nc4 Nd7 Rc7 Nxb6 Rxb7 Rxc4 Rxb6 Rc2 Rd6 h6 h4 Kf6 Rd7 g5 h5 Re2 g4 Ra2 Rd8 Ra7 Rh8 Kg7 Re8 Ra6 Kf2 f6 Re7+ Kg8 Ke3 e5 Re8+ Kf7 Rh8 Kg7 Re8 Kf7 Rh8 Kg7 Re8 Kf7", "id": "LmH0rMJN", "rated": true, "url": "http://lichess.org/LmH0rMJN/white", "status": "draw", "timestamp": 1460225264924, "variant": "standard", "perf": "classical", "turns": 98, "players": {"white": {"userId": "whiznl", "ratingDiff": 0, "rating": 1828, "analysis": {"blunder": 0, "mistake": 5, "inaccuracy": 3}}, "black": {"userId": "esea56", "ratingDiff": 0, "rating": 1816, "analysis": {"blunder": 0, "mistake": 1, "inaccuracy": 3}}}}, {"speed": "classical", "clock": {"increment": 5, "initial": 300, "totalTime": 500}, "moves": "e4 c6 d4 d5 e5 Bf5 Bd3 Bxd3 Qxd3 e6 Nf3 c5 Bg5 Qb6 b3 Nc6 dxc5 Bxc5 O-O Nge7 Bxe7 Nxe7 Nc3 a6 Na4 Qc6 Nxc5 Qxc5 Rac1 O-O c4 Rac8 h3 b5 cxd5 Qxd5 Qxd5 Nxd5 Rfd1 Nc3 Rc2 Nxd1", "id": "8DugnVJW", "rated": true, "url": "http://lichess.org/8DugnVJW/white", "status": "resign", "timestamp": 1460190755657, "winner": "black", "variant": "standard", "perf": "classical", "turns": 42, "players": {"white": {"userId": "mowiestar", "ratingDiff": -15, "rating": 1920, "analysis": {"blunder": 1, "mistake": 1, "inaccuracy": 0}}, "black": {"userId": "whiznl", "ratingDiff": 17, "rating": 1811, "analysis": {"blunder": 0, "mistake": 0, "inaccuracy": 0}}}}, {"speed": "classical", "clock": {"increment": 5, "initial": 300, "totalTime": 500}, "moves": "d4 d5 Nf3 e6 Nc3 Nf6 Bd2 c5 e3 Nc6 Be2 Qb6 Na4 Qc7 dxc5 Nd8 b4 a5 Nb6 Ra7 Bb5+ Bd7 Bxd7+ Nxd7 Nxd7 Qxd7 a3 Qc7 Bc3 b6 Be5 Qb7 Bd4 Nc6 cxb6 Ra6 Bc5 Bxc5 bxc5 Ne7 Nd4 O-O Qd3 Rc8 c6 Nxc6 Rb1 Nxd4 exd4 Rxb6 Rxb6 Qxb6 O-O Qb2 Qb3 Qxd4 Qb7 Qc4 Rc1 Qc6 Qxc6 Rxc6 Kf1 Rc3 a4 Ra3 c4 g6 cxd5 exd5 Rc5 Rxa4 Rxd5 Ra1+ Ke2 a4 Kd2 a3 Kc2 Ra2+ Kb3 Rxf2 Kxa3 Rxg2 Kb4 Rxh2 Kc3 Re2 Kd3 Re6 Kd4 h5 Rg5 Kg7 Kd5 Kf6 Rg1 Ke7 Rg5 Rf6 Ke4 Re6+ Kf4 Rf6+ Kg3 Rf5 Kh4 Rxg5 Kxg5 Ke6 Kh4 Kf5 Kh3 Kf4 Kh4 f5 Kh3 Kg5 Kg3 h4+ Kh3 f4 Kh2 Kg4 Kg2 h3+ Kh2 f3 Kg1 Kg3 Kh1 g5 Kg1 Kf4 Kh1 f2 Kh2 g4", "id": "W3y3Lrrw", "rated": true, "url": "http://lichess.org/W3y3Lrrw/white", "status": "resign", "timestamp": 1460114418063, "winner": "black", "variant": "standard", "perf": "classical", "turns": 138, "players": {"white": {"userId": "gunter44", "ratingDiff": -13, "rating": 1894}, "black": {"userId": "whiznl", "ratingDiff": 18, "rating": 1793}}}, {"speed": "classical", "clock": {"increment": 5, "initial": 300, "totalTime": 500}, "moves": "d4 d5 c4 e6 Nc3 Nf6 Nf3 c5 e3 cxd4 Nxd4 dxc4 Bxc4 e5 Ndb5 Qxd1+ Nxd1 Na6 Ndc3 Bb4 Bd2 O-O a3 Be7 Nd5 Nxd5 Bxd5 Bd7 Bc4 Nc5 Bb4 a6 Nc3 b5 Be2 a5 Bxc5 Bxc5 Bxb5 Bxb5 Nxb5 Rab8 a4 Bb4+ Nc3 Rfc8 Rc1 Rc4 O-O Bxc3 Rxc3 Rxa4 Rc2 Rab4 Rb1 a4 Rbc1 g6 Rb1 a3 g3 Rxb2 Rbxb2 axb2", "id": "QSVepIda", "rated": true, "url": "http://lichess.org/QSVepIda/black", "status": "resign", "timestamp": 1460113579462, "winner": "black", "variant": "standard", "perf": "classical", "turns": 64, "players": {"white": {"userId": "whiznl", "ratingDiff": -10, "rating": 1803, "analysis": {"blunder": 0, "mistake": 3, "inaccuracy": 3}}, "black": {"userId": "atomvain", "ratingDiff": 9, "rating": 1881, "analysis": {"blunder": 0, "mistake": 0, "inaccuracy": 0}}}}, {"speed": "classical", "clock": {"increment": 5, "initial": 300, "totalTime": 500}, "moves": "d4 f5 c4 Nf6 Nc3 e6 Nf3 Be7 g3 h5 h4 b6 Bg5 Bb7 e3 Ng4 Bxe7 Qxe7 Bg2 d6 O-O Nd7 Ng5 c6 Nh3 O-O-O d5 cxd5 cxd5 e5 e4 g6 Qd3 Nc5 Qc4 Kb8 exf5 gxf5 Rfe1 e4 Nf4 Rh6 f3 Ne5 Qf1 Rg8 fxe4 Rxg3 exf5 Qxh4 Nfe2 Ng4 Qf4 Qh2+", "id": "7tkLSqek", "rated": true, "url": "http://lichess.org/7tkLSqek/black", "status": "resign", "timestamp": 1460053794065, "winner": "black", "variant": "standard", "perf": "classical", "turns": 54, "players": {"white": {"userId": "whiznl", "ratingDiff": -12, "rating": 1815, "analysis": {"blunder": 2, "mistake": 2, "inaccuracy": 4}}, "black": {"provisional": true, "userId": "chesscopa", "ratingDiff": 41, "rating": 1816, "analysis": {"blunder": 0, "mistake": 2, "inaccuracy": 3}}}}, {"speed": "classical", "clock": {"increment": 5, "initial": 300, "totalTime": 500}, "moves": "d4 d5 e3 e6 Nf3 Nf6 Ne5 c5 Nc3 Nc6 Bb5 Bd7 Bxc6 bxc6 O-O Qc7 f4 Bc8 a4 a5 b3 Ba6 Rf2 cxd4 exd4 Bd6 Ba3 Bb4 Bxb4 axb4 Ne2 Ne4 Rf3 Qb6 Ng3 Nc3 Rxc3 bxc3 Nh5 Rg8 a5 Qb4 Ra4 Qb5 h3 Qe2 Qxe2 Bxe2 Ng3 Bb5 Ra3 Ke7 b4 f6 Nf3 Kd6 Rxc3 Ba4 f5 Rab8 fxe6 Kxe6 Ra3 Rxb4 c3 Rc4 Nd2 Bb5 Nxc4 Bxc4 a6 Ra8 a7 Kd7 Nf5 g6 Ne3 Bb5 Kf2 Kc7 Kg3 Kb7 Kf4 Rxa7 Rxa7+ Kxa7 g4 Kb6 h4 c5 h5 cxd4 cxd4 Kc6 h6 Kd6 g5 Ke6 Ng4 fxg5+ Kxg5 Be2 Nf6 Bd3 Nxh7 Kf7 Nf6 Kf8 h7 Kg7 Nxd5 Kxh7 Nf4 Be4 d5 Bxd5 Nxd5 Kg7 Nf4 Kf7 Nxg6", "id": "XvyffiAi", "rated": true, "url": "http://lichess.org/XvyffiAi/white", "status": "draw", "timestamp": 1460051831595, "variant": "standard", "perf": "classical", "turns": 121, "players": {"white": {"userId": "alex83", "ratingDiff": 0, "rating": 1827, "analysis": {"blunder": 1, "mistake": 7, "inaccuracy": 3}}, "black": {"userId": "whiznl", "ratingDiff": 0, "rating": 1815, "analysis": {"blunder": 1, "mistake": 7, "inaccuracy": 1}}}}, {"speed": "classical", "clock": {"increment": 5, "initial": 300, "totalTime": 500}, "moves": "e4 c6 Bc4 d5 exd5 cxd5 Bd3 Nc6 Bb5 e5 f4 e4 d4 f5 Nh3 h6 O-O a6 Be2 Qb6 c3 Bd7 Bh5+ g6 Bxg6+ Kd8 Qh5 Nge7 Ng5 Rg8 Nf7+ Kc7 Bxf5 Nxf5 Ne5 Nce7 b3 Be8 Qh3 Nxd4", "id": "qmcywwqU", "rated": true, "url": "http://lichess.org/qmcywwqU/black", "status": "outoftime", "timestamp": 1460047467556, "winner": "black", "variant": "standard", "perf": "classical", "turns": 40, "players": {"white": {"userId": "conan66", "ratingDiff": -5, "rating": 1592, "analysis": {"blunder": 1, "mistake": 1, "inaccuracy": 4}}, "black": {"userId": "whiznl", "ratingDiff": 7, "rating": 1808, "analysis": {"blunder": 0, "mistake": 3, "inaccuracy": 2}}}}, {"speed": "classical", "clock": {"increment": 5, "initial": 300, "totalTime": 500}, "moves": "d4 Nf6 c4 e5 dxe5 Ng4 Nf3 Nc6 Bf4 Bb4+ Nbd2 Qe7 a3 Ngxe5 Nxe5 Nxe5 e3 Bxd2+ Qxd2 d6 Be2 O-O O-O Be6 Qc3 Ng6 Rfd1 Bd7 Bf3 Rab8 a4 Nxf4 exf4 b6 a5 Qh4 g3 Qh6 axb6 axb6 Ra7 Rbc8 Bb7 Rb8 Ba6 Ra8 Rxc7 Ba4 Bb7 Bxd1 Bxa8 Rxa8 Qd2 Bf3 Qe1 Qh3", "id": "01yySoV8", "rated": true, "url": "http://lichess.org/01yySoV8/black", "status": "resign", "timestamp": 1460044663019, "winner": "black", "variant": "standard", "perf": "classical", "turns": 56, "players": {"white": {"userId": "whiznl", "ratingDiff": -10, "rating": 1818, "analysis": {"blunder": 2, "mistake": 0, "inaccuracy": 1}}, "black": {"userId": "gammarax", "ratingDiff": 14, "rating": 1900, "analysis": {"blunder": 0, "mistake": 0, "inaccuracy": 2}}}}, {"speed": "classical", "clock": {"increment": 5, "initial": 300, "totalTime": 500}, "moves": "d4 d5 c4 dxc4 e3 Bf5 Bxc4 a6 a4 Nc6 Nc3 Nb4 e4 Bg6 Qb3 a5 Nf3 f5 e5 Nh6 h3 f4 Bxf4 Nc2+ Kd2 Nxa1 Rxa1 Nf5 Qxb7 Nxd4 Nxd4 e6 Qc6+ Ke7 Qxe6#", "id": "u2YImCLu", "rated": true, "url": "http://lichess.org/u2YImCLu/white", "status": "mate", "timestamp": 1460044271911, "winner": "white", "variant": "standard", "perf": "classical", "turns": 35, "players": {"white": {"userId": "whiznl", "ratingDiff": 1, "rating": 1817}, "black": {"userId": "marinogiudice", "ratingDiff": -1, "rating": 1228}}}, {"speed": "classical", "clock": {"increment": 5, "initial": 300, "totalTime": 500}, "moves": "e4 c6 f4 d5 e5 Bf5 d4 e6 Nf3 c5 c3 Nc6 Bb5 a6 Bxc6+ bxc6 O-O Qb6 Kh1 Bg4 dxc5 Bxc5 h3 Bxf3 Qxf3 Ne7 b4 Bxb4 cxb4 Qxb4 Bd2 Qd4 Bc3 Qc4 Nd2 Qc5 a3 Rb8 Rfb1 O-O Bb4 Qa7 Kh2 Rb7 Bc5 Rxb1 Bxa7 Rxa1 Bc5 Re8 Bxe7 Rxe7 Qc3 Ra2 Nf3 Rc7 Qb3 Ra1 Qb8+", "id": "GKFqTcFd", "rated": true, "url": "http://lichess.org/GKFqTcFd/white", "status": "resign", "timestamp": 1459884475578, "winner": "white", "variant": "standard", "perf": "classical", "turns": 59, "players": {"white": {"userId": "fibulon", "ratingDiff": 9, "rating": 1901, "analysis": {"blunder": 1, "mistake": 3, "inaccuracy": 0}}, "black": {"userId": "whiznl", "ratingDiff": -11, "rating": 1828, "analysis": {"blunder": 2, "mistake": 4, "inaccuracy": 2}}}}, {"speed": "classical", "clock": {"increment": 5, "initial": 300, "totalTime": 500}, "moves": "d4 Nf6 c4 d5 cxd5 Qxd5 Nc3 Qc4 e3 Qb4 a3 Qb6 Nf3 Bg4 Be2 c6 b4 Nd5 Bb2 Nxc3 Bxc3 Nd7 a4 e6 Qb3 Bd6 h3 Bxf3 Bxf3 O-O O-O Bb8 b5 cxb5 axb5 Qc7 g3 Nb6 Ba5 Qc4 Qxc4 Nxc4 Bxb7 Nxa5 Rxa5 Bc7 Raa1 Rab8 Rxa7 Rxb7 Rxb7", "id": "6E1fk6yW", "rated": true, "url": "http://lichess.org/6E1fk6yW/white", "status": "resign", "timestamp": 1459879746996, "winner": "white", "variant": "standard", "perf": "classical", "turns": 51, "players": {"white": {"userId": "whiznl", "ratingDiff": 6, "rating": 1822, "analysis": {"blunder": 0, "mistake": 2, "inaccuracy": 2}}, "black": {"userId": "rbktiger", "ratingDiff": -4, "rating": 1557, "analysis": {"blunder": 1, "mistake": 3, "inaccuracy": 0}}}}, {"speed": "classical", "clock": {"increment": 5, "initial": 300, "totalTime": 500}, "moves": "e4 c6 g4 d5 Bg2 Nf6 exd5 Bxg4 Bf3 Bxf3 Nxf3 cxd5 Ne5 e6 d4 Nc6 Bg5 Be7 Nxc6 bxc6 Qf3 O-O c3 Ne4 Bxe7 Qxe7 Na3 Rab8 c4 Rxb2 cxd5 exd5 Rc1 Ng5+ Qe3 Re8 O-O Qxe3 fxe3 Rxe3 Rxc6 g6 Rc8+ Kg7 Nb1 Nh3+ Kh1 Ree2 Nc3 Rxh2#", "id": "SjbeXfgD", "rated": true, "url": "http://lichess.org/SjbeXfgD/black", "status": "mate", "timestamp": 1459879212387, "winner": "black", "variant": "standard", "perf": "classical", "turns": 50, "players": {"white": {"userId": "tispiezzo", "ratingDiff": -4, "rating": 1572}, "black": {"userId": "whiznl", "ratingDiff": 6, "rating": 1816}}}, {"speed": "classical", "clock": {"increment": 5, "initial": 300, "totalTime": 500}, "moves": "e4 c6 d4 d5 e5 Bf5 Nf3 e6 Be2 c5 c3 Nc6 O-O Bg4 h3 Bxf3 Bxf3 Nge7 Bg5 Qb6 Be3 cxd4 Bxd4 Nxd4 cxd4 Nf5 Qa4+ Qc6 Qxc6+ bxc6 Rc1 Nxd4 Nc3", "id": "dB4YSEfA", "rated": true, "url": "http://lichess.org/dB4YSEfA/white", "status": "resign", "timestamp": 1459786588983, "winner": "black", "variant": "standard", "perf": "classical", "turns": 33, "players": {"white": {"userId": "itigran", "ratingDiff": -14, "rating": 1933, "analysis": {"blunder": 0, "mistake": 0, "inaccuracy": 3}}, "black": {"userId": "whiznl", "ratingDiff": 21, "rating": 1795, "analysis": {"blunder": 0, "mistake": 0, "inaccuracy": 2}}}}, {"speed": "classical", "clock": {"increment": 5, "initial": 300, "totalTime": 500}, "moves": "e4 c6 d4 d5 f3 e6 Bd3 c5 Ne2 Nc6 O-O Nxd4 Nxd4 cxd4 Bb5+ Bd7 Bxd7+ Qxd7 Qxd4 Qc6 exd5 exd5 Re1+ Be7 Qxg7 Qf6 Rxe7+ Qxe7 Qxh8 Qe1#", "id": "8vZMrFpK", "rated": true, "url": "http://lichess.org/8vZMrFpK/white", "status": "mate", "timestamp": 1459619387026, "winner": "black", "variant": "standard", "perf": "classical", "turns": 30, "players": {"white": {"userId": "yilmazibo", "ratingDiff": -11, "rating": 1818, "analysis": {"blunder": 1, "mistake": 2, "inaccuracy": 2}}, "black": {"userId": "whiznl", "ratingDiff": 17, "rating": 1778, "analysis": {"blunder": 0, "mistake": 3, "inaccuracy": 1}}}}, {"speed": "classical", "clock": {"increment": 5, "initial": 300, "totalTime": 500}, "moves": "e4 c6 d4 d5 exd5 cxd5 Nf3 Nf6 Bd3 Bg4 h3 Bxf3 Qxf3 Nc6 Be3 Qb6", "id": "mKmkABFe", "rated": true, "url": "http://lichess.org/mKmkABFe/black", "status": "timeout", "timestamp": 1459607611355, "winner": "black", "variant": "standard", "perf": "classical", "turns": 16, "players": {"white": {"userId": "thunderdelta", "ratingDiff": -11, "rating": 1740}, "black": {"userId": "whiznl", "ratingDiff": 14, "rating": 1764}}}, {"speed": "classical", "clock": {"increment": 5, "initial": 300, "totalTime": 500}, "moves": "d4 Nc6 Nf3 f6 c4 e5 d5 e4 Nfd2 Ne5 b3 Ne7 Nxe4 d6 Nbc3 Bg4 h3 Bf5 e3 g5 Ng3 g4 Nxf5 Nxf5 hxg4 Rg8 gxf5 Ng4 Rxh7 Rg7 Rxg7 Bxg7 Qxg4 c6 Qxg7 cxd5 Qg8+ Kd7 Qxd8+ Kxd8 Nxd5 Kd7 Nxf6+ Kc6 Ba3 Re8 Nxe8 Kd7 Nf6+ Ke7 Nd5+ Kd7 f6 Ke8 Bxd6 Kf7 Bd3 b6", "id": "c0s9MKij", "rated": true, "url": "http://lichess.org/c0s9MKij/white", "status": "resign", "timestamp": 1459360515219, "winner": "white", "variant": "standard", "perf": "classical", "turns": 58, "players": {"white": {"userId": "whiznl", "ratingDiff": 7, "rating": 1757}, "black": {"provisional": true, "userId": "hkanwar", "ratingDiff": -15, "rating": 1531}}}, {"speed": "classical", "clock": {"increment": 5, "initial": 300, "totalTime": 500}, "moves": "d4 d5 c4 e6 Nc3 Nf6 Nf3 c5 cxd5 Nxd5 e4 Nxc3 bxc3 cxd4 cxd4 Bb4+ Bd2 Bxd2+ Qxd2 O-O Be2 b6 O-O Bb7 Rac1 Nc6 Rfd1 Rc8 Qf4 Nb4 a3 Rxc1 Rxc1 Na2 Rc7 Qb8 Ng5 f6 Nxe6 Re8 Bc4 Bc8 Nxg7+ Kf8 Qxf6#", "id": "5hxLyQor", "rated": true, "url": "http://lichess.org/5hxLyQor/black", "status": "mate", "timestamp": 1459348161000, "winner": "white", "variant": "standard", "perf": "classical", "turns": 45, "players": {"white": {"userId": "oissa", "ratingDiff": 12, "rating": 1743}, "black": {"userId": "whiznl", "ratingDiff": -16, "rating": 1773}}}, {"speed": "classical", "clock": {"increment": 5, "initial": 300, "totalTime": 500}, "moves": "d4 d5 c4 e6 Nf3 Nf6 Bg5 c5 e3 cxd4 Nxd4 Nc6 Nc3 Be7 Nxc6 bxc6 Bd3 O-O O-O Rb8 Qc2 Re8 b3 Ba6 Rac1 Qa5 e4 d4 Ne2 e5 f4 exf4 Nxd4 Qxg5 Nxc6 Rb7 h3 Qc5+ Kh1 Qxc6", "id": "iiS9qreb", "rated": true, "url": "http://lichess.org/iiS9qreb/white", "status": "resign", "timestamp": 1459280886869, "winner": "black", "variant": "standard", "perf": "classical", "turns": 40, "players": {"white": {"userId": "adamk", "ratingDiff": -11, "rating": 1782, "analysis": {"blunder": 1, "mistake": 4, "inaccuracy": 1}}, "black": {"userId": "whiznl", "ratingDiff": 18, "rating": 1755, "analysis": {"blunder": 1, "mistake": 3, "inaccuracy": 0}}}}, {"speed": "classical", "clock": {"increment": 5, "initial": 300, "totalTime": 500}, "moves": "d4 Nf6 c4 e6 Nc3 d5 Nf3 c6 e3 Bb4 a3 Bxc3+ bxc3 Qb6 a4 Ne4 Qc2 Qa6 Bd3 Nd6 c5 Nb5 Bb2 Nxd4 cxd4 Qa5+ Bc3 Qd8 O-O O-O Bxh7+ Kh8 Bd3 Qf6 e4 Nd7 e5 Qh6 Bd2 Qh5 h3 f5 Nh2 Rf7 Qd1 Qg6 Re1 b6 cxb6 Nxb6 Re3 Nc4 Rg3 Qh7 Bxc4 dxc4 Qe2 Ba6 Qf3 Rc8 Qf4 Kg8 Qg5 c3 Bxc3 c5 Bb2 cxd4 Bxd4 Rc4 Be3 Re4 Nf3 f4 Bxf4 Rexf4 Qd8+ Rf8 Qg5 R4f5 Qg4 Bb7 Ng5 Qh6 Nxe6 R8f7 Nc5 Bc8 Qe4 Rxf2 e6 R7f4 e7 Rxe4 Nxe4 Bd7 Rd1 Qe6 Nxf2 Qxe7 Kh2 Bxa4 Rd4 Bd7 Rgd3 Bc6 g3 Qe2 Kg1 Bb5 Rd2 Qf1+ Kh2 Bc6 Rd8+ Kh7 Rd1 Qg2#", "id": "lPVSgSHb", "rated": true, "url": "http://lichess.org/lPVSgSHb/black", "status": "mate", "timestamp": 1459189361831, "winner": "black", "variant": "standard", "perf": "classical", "turns": 118, "players": {"white": {"userId": "whiznl", "ratingDiff": -13, "rating": 1768, "analysis": {"blunder": 8, "mistake": 9, "inaccuracy": 6}}, "black": {"userId": "captncarter", "ratingDiff": 10, "rating": 1809, "analysis": {"blunder": 3, "mistake": 11, "inaccuracy": 7}}}}, {"speed": "classical", "clock": {"increment": 5, "initial": 300, "totalTime": 500}, "moves": "d4 d5 c4 e6 Nc3 Nf6 Bg5 c5 dxc5 Bxc5 cxd5 Qb6 Be3 Bxe3 fxe3 exd5 Qd2 O-O O-O-O Rd8 Nf3 Nc6 Nd4 Be6 g3 Ne4 Nxe4 dxe4 Qc3 Bxa2 Bg2 Rd6 Bxe4 Rad8 Bd3 Nxd4 exd4 Rxd4 Rd2 Qb3 Qxb3 Bxb3 Rf1 Bc4 Rfd1 Bxd3 exd3 Rc8+ Kb1 f5 h3 Rcd8 b3 g5 Kb2 Rc8 Rf2 Rd5 d4 Kf7 g4 f4 h4 h6 hxg5 hxg5 Rh2 Kg6 Rdd2 b5 b4 Rc4 Kb3 Rcxd4 Rxd4 Rxd4 Rh8 f3 Rf8 Rf4 Rg8+ Kf6 Rf8+ Ke5 Re8+ Kd4 Rd8+ Ke3 Re8+ Kf2 Re7 Kg3 Rxa7 f2 Rb7 f1=Q Rg7 Kxg4 Rxg5+ Kxg5 Kc3 Qc4+ Kd2 Rd4+ Ke3 Qe2+ Kxd4 Qc4+ Ke5 Qxb4 Kd5 Qc4+ Ke5 Kg4 Kf6 Kf4 Kg6 Ke5 Kg5 Qf4+ Kg6 Ke6 Kh5 Qf5+ Kh4 Qg6 Kh3 Kf5 Kh2 Kf4 Kh1 Kf3 Kh2 Qg2#", "id": "icZ3rFVs", "rated": true, "url": "http://lichess.org/icZ3rFVs/white", "status": "mate", "timestamp": 1459187992142, "winner": "black", "variant": "standard", "perf": "classical", "turns": 134, "players": {"white": {"userId": "dillip007", "ratingDiff": -12, "rating": 1805}, "black": {"userId": "whiznl", "ratingDiff": 20, "rating": 1748}}}, {"speed": "classical", "clock": {"increment": 5, "initial": 300, "totalTime": 500}, "moves": "d4 e6 c4 c5 d5 Nf6 Nc3 Be7 e4 exd5 cxd5 O-O Nf3 Re8 Bc4 d6 O-O Bg4 h3 Bh5 a3 Nbd7 b4 Bf8 Re1 Ne5 g4 Bg6 bxc5 Nxc4 Qb3 Na5 Qb5 dxc5 Bg5 b6 Kg2 h6 Bh4 Nb7 e5 Nd6 exd6 Rxe1 Rxe1 Qxd6 Qc6 Nxd5 Qxa8 Nf4+ Kh2 Nd3+ Bg3 Qf6 Re8 Qxf3 Rxf8+ Kh7 Qxf3 Ne1 Qe2", "id": "DMtT3AYf", "rated": true, "url": "http://lichess.org/DMtT3AYf/white", "status": "outoftime", "timestamp": 1459186573852, "winner": "white", "variant": "standard", "perf": "classical", "turns": 61, "players": {"white": {"userId": "whiznl", "ratingDiff": 10, "rating": 1738, "analysis": {"blunder": 1, "mistake": 6, "inaccuracy": 3}}, "black": {"userId": "bongoman", "ratingDiff": -6, "rating": 1587, "analysis": {"blunder": 3, "mistake": 7, "inaccuracy": 1}}}}, {"speed": "classical", "clock": {"increment": 5, "initial": 300, "totalTime": 500}, "moves": "d4 d5 c4 e6 Nc3 Nf6 Bg5 c5 Bxf6 Qxf6 cxd5 exd5 Nxd5 Qxd4 Qxd4 cxd4 Nc7+", "id": "33M9FmQe", "rated": true, "url": "http://lichess.org/33M9FmQe/white", "status": "resign", "timestamp": 1459186361201, "winner": "white", "variant": "standard", "perf": "classical", "turns": 17, "players": {"white": {"userId": "pimp9000", "ratingDiff": 10, "rating": 1806}, "black": {"userId": "whiznl", "ratingDiff": -14, "rating": 1752}}}, {"speed": "classical", "clock": {"increment": 5, "initial": 300, "totalTime": 500}, "moves": "Nf3 d5 d4 Nf6 c3 Bf5 g3 e6 Bg2 c5 O-O Nc6 dxc5 Bxc5 b4 Bd6 Nbd2 O-O Nh4 Be5 Bb2 Bg4 f3 Bh5 g4 Bg6 Nxg6 hxg6 f4 Nxg4 fxe5 Ne3 Qe1 Nxf1 Qxf1 Nxe5 Qf4 Qb6+ e3 Nd3 Qh4 Nxb2 Rf1 Qxe3+ Kh1 Qxd2 h3 Qh6 Qd4 Nc4 Rf4 Nd6 Rh4 Qc1+ Kh2 Qg5 Rg4 Qf6 Rf4 Qxd4 Rxd4 Nf5 Rf4 Rfc8 Rf3 Rc4", "id": "wx1WoVMi", "rated": true, "url": "http://lichess.org/wx1WoVMi/black", "status": "timeout", "timestamp": 1459185630992, "winner": "black", "variant": "standard", "perf": "classical", "turns": 66, "players": {"white": {"userId": "zip1zip", "ratingDiff": -6, "rating": 1596, "analysis": {"blunder": 3, "mistake": 1, "inaccuracy": 2}}, "black": {"userId": "whiznl", "ratingDiff": 12, "rating": 1740, "analysis": {"blunder": 1, "mistake": 0, "inaccuracy": 3}}}}, {"speed": "classical", "clock": {"increment": 5, "initial": 300, "totalTime": 500}, "moves": "d4 Nf6 c4 g6 Nc3 Bg7 e4 d6 Nf3 Nc6 Be2 e5 dxe5 dxe5 Qxd8+ Nxd8 O-O O-O b3 Nc6 Bb2 Bg4 h3 Bxf3 Bxf3 Rad8 Rad1 Nd4 Rd3 Rd7 Ne2 Nxe2+ Bxe2 Rxd3 Bxd3 Rd8 Bc2 Ne8 Rd1 Rxd1+ Bxd1 f6 Bc1 Bf8 f4 Bd6 g3 c5 Kg2 Ng7 fxe5 Bxe5 a4 b6 Bg4 Kf7 Bd7 Ne6 Kf3 Ke7 Bc8 Nd4+ Ke3 Nxb3 Bd2 Bd4+ Kd3 Nxd2 Kxd2 Kd6 Bg4 Ke5 Kd3 h5 Bd7 Bf2 g4 hxg4 hxg4 g5 Bf5 Bd4 Bd7 Kf4 Bf5 Ke5 Bd7 Kd6 Bf5 Kc7 Be6 a6 Bf5 b5 axb5 axb5 cxb5 Kb6 Kc4 Be3 Bd7 Bf4 Bf5 Be5 Bd7 Bd4 Bf5 Kc7 Be6 Be3 Bd5 Kb6 Bc6 Bd4 Bd7 Kc7 Be8 Kd8 Bc6 Kc7 Bd5 Kd6 b6 Ke7 b7 Be5 Kxc5 Kd7 Kb6 Bc7+ Ka7 Kd6 b8=Q Bxb8+ Kxb8 Ke5 Kc7 Kf4 Kd6 Kxg4 Be6+ Kf4 Kd5 g4 Bxg4 Kxg4 Ke6 Kg5 e5 f5", "id": "baLM7Umz", "rated": true, "url": "http://lichess.org/baLM7Umz/white", "status": "outoftime", "timestamp": 1459184499471, "winner": "black", "variant": "standard", "perf": "classical", "turns": 150, "players": {"white": {"userId": "whiznl", "ratingDiff": -21, "rating": 1761}, "black": {"userId": "richarh", "ratingDiff": 13, "rating": 1701}}}, {"speed": "classical", "clock": {"increment": 5, "initial": 300, "totalTime": 500}, "moves": "d4 d5 Bf4 Nf6 h3 c5 c3 Nc6 e3 e6 Nf3 Bd6 Bg5 O-O Be2 h6 Bh4 cxd4 cxd4 Be7 Bg3 Ne4 Bh2 Bb4+ Nfd2 Qa5 a3 b6 Bf3 Ng5 O-O Ba6 Re1 f6 Nc3 Bxc3 bxc3 Qxc3 Rc1 Nxf3+ Nxf3 Qxa3 Rxc6 Rfe8 Qa1 Qd3 Rd1 Qb5 Rdc1 Rac8 Rxc8 Rxc8 Rxc8+ Bxc8 Bg3 Ba6 Bb8 Kf7 Bxa7 Qc4 Bxb6 Qb5 Bc5 Kg6 Nd2 Kf5 Qb1+ Kg5 Qxb5 Bxb5 Nb3 Bc4 Na5 e5 Nxc4 dxc4 dxe5 fxe5 Bb4 Kf5 Kf1 Ke4 Ke2 g5 Bc3 Kd5 Kf3 Kc5 Ke4 Kd6 Bb4+ Kc6 Bc3 Kb5 Kxe5 Ka4 Kd4 Kb3 e4 Ka4 e5 Kb5 e6 Kc6 e7 Kd7 Kxc4 Kxe7 Kd4 Ke6 Ke4 Kf7 Kf5 Kg8 Kg6 Kf8 Kxh6 Kf7 Kxg5 Kg8 h4 Kh7 h5 Kg8 h6 Kh7 f4 Kg8 f5 Kh7 f6 Kh8 f7+ Kh7 f8=Q", "id": "2m7MgUYv", "rated": true, "url": "http://lichess.org/2m7MgUYv/black", "status": "stalemate", "timestamp": 1459115111738, "variant": "standard", "perf": "classical", "turns": 135, "players": {"white": {"userId": "sgroppenpedons", "ratingDiff": 1, "rating": 1715, "analysis": {"blunder": 4, "mistake": 5, "inaccuracy": 10}}, "black": {"userId": "whiznl", "ratingDiff": -2, "rating": 1763, "analysis": {"blunder": 5, "mistake": 7, "inaccuracy": 10}}}}, {"speed": "classical", "clock": {"increment": 5, "initial": 300, "totalTime": 500}, "moves": "d4 d5 c4 Bf5 cxd5 Qxd5 Nc3 Qd8 e4 Bg6 Nf3 Nf6 Bd3 h6 O-O e6 a3 Be7 Re1 O-O h3 c6 Bf4 Ne8 b4 a5 b5 c5 d5 Bf6 Ne5 Bh7 Qg4 Kh8 Rad1 Bxe5 Bxe5 Nf6 Qg3 Nbd7 Bd6 Re8 e5 Nxd5 Bxh7 Nxc3 Qxc3 Kxh7 Bxc5 Rc8 Qd3+ Kg8 Be3 Nxe5 Qxd8 Rcxd8 Rxd8 Rxd8 Bb6 Rd5 Bd4 Nc4 a4 Rxd4", "id": "miZxqFUx", "rated": true, "url": "http://lichess.org/miZxqFUx/white", "status": "resign", "timestamp": 1458848990560, "winner": "black", "variant": "standard", "perf": "classical", "turns": 64, "players": {"white": {"userId": "whiznl", "ratingDiff": -22, "rating": 1785, "analysis": {"blunder": 1, "mistake": 6, "inaccuracy": 6}}, "black": {"provisional": true, "userId": "leonwali", "ratingDiff": 58, "rating": 1696, "analysis": {"blunder": 0, "mistake": 7, "inaccuracy": 2}}}}, {"speed": "classical", "clock": {"increment": 5, "initial": 300, "totalTime": 500}, "moves": "d4 d5 c4 Nf6 cxd5 Nxd5 e4 Nb6 Nc3 e5 Nf3 exd4 Qxd4 Qxd4 Nxd4 Bb4 Bd2 O-O a3 Bxc3 Bxc3 Nc4 Bxc4 Kh8 Nf5 Bxf5 exf5 Re8+ Be2 Nc6 O-O Ne5 Bxe5 Rxe5 Bd3 Rd5 Rfd1 Rad8 Bc2 Rc5 Rxd8#", "id": "gzWHhy65", "rated": true, "url": "http://lichess.org/gzWHhy65/white", "status": "mate", "timestamp": 1458848660554, "winner": "white", "variant": "standard", "perf": "classical", "turns": 41, "players": {"white": {"userId": "whiznl", "ratingDiff": 21, "rating": 1764, "analysis": {"blunder": 1, "mistake": 1, "inaccuracy": 1}}, "black": {"userId": "ezzeldeen", "ratingDiff": -10, "rating": 1755, "analysis": {"blunder": 3, "mistake": 0, "inaccuracy": 3}}}}, {"speed": "classical", "clock": {"increment": 5, "initial": 300, "totalTime": 500}, "moves": "d4 d5 Nc3 Nf6 Bf4 e6 Nb5 Na6 Qd2 c6 Nc3 Bb4 a3 Ba5 b4 Bb6 e3 O-O Bxa6 bxa6 Na4 a5 Nc5 axb4 axb4 Bxc5 bxc5 Ne4 Qe2 Qe7 g3 a5 f3 Nc3 Qd2 Nb5 Rxa5 Ba6 Ne2 f6 Nc3 Nxc3 Bd6 Qb7 Kf2 Qb4 Bxf8 Ne4+ fxe4 Qxd2+ Kf3 Qxa5 Bd6 g5 e5 fxe5 Bxe5 Rf8+ Kg4 Rf5 Kh5 Rxe5 dxe5 Qd8 Rf1 Kg7 Rf6 Be2+ Kxg5 Qe7 h4 h6+ Kf4 Qxf6+ exf6+ Kxf6 g4 h5 gxh5 Bxh5 c3 Be2 e4 dxe4 Kxe4 e5 Ke3 Bc4 Kf3 Kf5 h5 e4+ Ke3 Ke5 h6 Bg8 Ke2 Kd5 Ke3 Bh7 c4+ Kxc4 Kf4 Kxc5 Ke3 Kc4 Kf4 Kd3 Ke5 e3 Kf6 e2 Kg7 Be4 h7 Bxh7 Kxh7 e1=Q", "id": "DXaRgfgw", "rated": true, "url": "http://lichess.org/DXaRgfgw/black", "status": "resign", "timestamp": 1458759474090, "winner": "black", "variant": "standard", "perf": "classical", "turns": 118, "players": {"white": {"userId": "govindadailha", "ratingDiff": -6, "rating": 1624}, "black": {"userId": "whiznl", "ratingDiff": 15, "rating": 1749}}}, {"speed": "classical", "clock": {"increment": 5, "initial": 300, "totalTime": 500}, "moves": "e4 c6 d4 d5 exd5 cxd5 Bb5+ Nc6 Bxc6+ bxc6 Na3 e6 c3 Bxa3 bxa3 Nf6 Rb1 O-O Bg5 Ba6 Qa4 Qc8 Bxf6 gxf6 Nf3 Bc4 Rb2 Qc7 Kd2 Rfb8 Rc2 Rb6 Rb1 Rxb1", "id": "PFh1EQeV", "rated": true, "url": "http://lichess.org/PFh1EQeV/black", "status": "resign", "timestamp": 1458755691279, "winner": "black", "variant": "standard", "perf": "classical", "turns": 34, "players": {"white": {"userId": "scalemusic", "ratingDiff": -2, "rating": 1277}, "black": {"userId": "whiznl", "ratingDiff": 4, "rating": 1745}}}, {"speed": "classical", "clock": {"increment": 5, "initial": 300, "totalTime": 500}, "moves": "d4 b6 e4 Bb7 Bd3 Na6 a3 c5 Qe2 Qc8 d5 Nf6 c4 g6 Nc3 Bg7 Nf3 d6 Rb1 Qg4 O-O Ng8 Bd2 Bh6 Bxh6 Nxh6 b4 Ng8 bxc5 dxc5 Na4 Nf6 Qe3 Nh5 h3 Qd7 Bc2 h6 g4 Rg8 Qxh6 O-O-O Nh2 f6 gxh5 gxh5+ Kh1 Qxh3 Rg1 Rxg1+ Rxg1 Qxa3 Qxh5 Nb4 Qf5+ Kb8 Qf4+ Ka8 Qd2 Qa2 Rc1 Rg8 Nf3 Rh8+ Kg2 Rg8+ Kf1 Rh8 Ng1 Rh2 Nf3 Rh1+ Ng1 Bc8 Kg2 Rh4 Nxb6+ axb6 Nf3 Rg4+ Kf1 Rf4 Nd4 Rxe4", "id": "H0o1OuMu", "rated": true, "url": "http://lichess.org/H0o1OuMu/white", "status": "outoftime", "timestamp": 1458725909236, "winner": "black", "variant": "standard", "perf": "classical", "turns": 84, "players": {"white": {"userId": "whiznl", "ratingDiff": -31, "rating": 1776, "analysis": {"blunder": 2, "mistake": 13, "inaccuracy": 3}}, "black": {"userId": "narnuche", "ratingDiff": 24, "rating": 1614, "analysis": {"blunder": 2, "mistake": 11, "inaccuracy": 4}}}}, {"speed": "classical", "clock": {"increment": 5, "initial": 300, "totalTime": 500}, "moves": "d4 d5 c4 e6 Nc3 Nf6 Nf3 c6 e3 Nbd7 a3 Be7 b4 O-O Bd3 dxc4 Bxc4 b5 Bd3 a6 Ne4 Nxe4 Bxe4 Bb7 O-O Nf6 Bc2 a5 Bb2 axb4 axb4 Bxb4 Qd3 Be7 g4 g6 g5 Nh5 h4 Qd5 e4 Qc4 Qxc4 bxc4 Nd2 f6 Nxc4 fxg5 hxg5 Rxa1 Bxa1 Bxg5 Ne5 Bf6 Nd7 Rf7 Nxf6+ Rxf6 d5 Rf8 dxe6 Re8 Bb3 Kf8 Rd1 Nf4 Rd7 Bc8 Rf7+ Kg8 Rxf4 Bxe6 Bxe6+ Rxe6 f3 Re8 Bd4 Rf8 Rxf8+ Kxf8 Kg2 Ke7 Kg3 Ke6 Bc5 Ke5 Kg4 Kf6 f4 h5+ Kh4 Kf7 Kg5 Kg7 e5 Kf7 Kh6 h4 Kg5 h3 Bg1 Ke6 Kxg6 c5 Kg5 c4 Kg4 c3 Kxh3 Kf5 Be3 Ke4 Bc1 c2 e6 Kd3 e7 Ke2 e8=Q+ Kd1 Ba3 Kd2 Qc8 Kd3 f5", "id": "MRCmbRFi", "rated": true, "url": "http://lichess.org/MRCmbRFi/white", "status": "resign", "timestamp": 1458594419562, "winner": "white", "variant": "standard", "perf": "classical", "turns": 125, "players": {"white": {"userId": "whiznl", "ratingDiff": 21, "rating": 1755}, "black": {"userId": "juan1243", "ratingDiff": -9, "rating": 1700}}}, {"speed": "classical", "clock": {"increment": 5, "initial": 300, "totalTime": 500}, "moves": "d4 d5 e3 e6 Nf3 Nf6 c4 c5 b3 cxd4 Nxd4 Nc6 Nc3 Bc5 cxd5 Nxd5 Ne4 Qb6 Bd2 Nxd4 exd4 Bxd4 Bc4 Bxa1 Qxa1 O-O O-O Qc6 Bb4 Nxb4", "id": "tvZKkPTo", "rated": true, "url": "http://lichess.org/tvZKkPTo/black", "status": "resign", "timestamp": 1458591590423, "winner": "black", "variant": "standard", "perf": "classical", "turns": 30, "players": {"white": {"userId": "mindfreak", "ratingDiff": -4, "rating": 1462}, "black": {"userId": "whiznl", "ratingDiff": 9, "rating": 1746}}}, {"speed": "classical", "clock": {"increment": 5, "initial": 300, "totalTime": 500}, "moves": "d4 e6 c4 Bb4+ Nc3 Ba5 Nf3 Nc6 a3 e5 e3 Nf6 b4 Bb6 c5 Bxc5 bxc5 Nxd4 exd4 exd4 Nb5 O-O Nbxd4 Re8+ Be2 c6 O-O Qa5 Qc2 Qc7 Bg5 Ng4 h3 Qh2+ Nxh2 Nxh2 Kxh2 Rxe2 Qxe2 d6 Qe8#", "id": "ta7TPqtl", "rated": true, "url": "http://lichess.org/ta7TPqtl/white", "status": "mate", "timestamp": 1458591108754, "winner": "white", "variant": "standard", "perf": "classical", "turns": 41, "players": {"white": {"userId": "whiznl", "ratingDiff": 1, "rating": 1745}, "black": {"provisional": true, "userId": "johnnymiglio", "ratingDiff": -3, "rating": 1088}}}, {"speed": "classical", "clock": {"increment": 5, "initial": 300, "totalTime": 500}, "moves": "e4 c6 Nc3 d5 exd5 cxd5 d4 Nc6 Bb5 a6 Bxc6+ bxc6 Nf3 Bg4 h3 Bxf3 Qxf3 e6 a3 Qb6 Ne2 c5 dxc5 Bxc5 O-O Nf6 b4 Bd4 Rb1 a5 Be3 Bxe3 Qxe3 Qxe3 fxe3 O-O Nd4 Rfb8 Nc6 Rb6 Nxa5 Ne4 Rbc1 Nd2 Rf2 Nc4 Nxc4 dxc4 Ra1 Rba6 Rf4 Rxa3 Rxa3 Rxa3 Rxc4 g6 Kf2 Kg7 g4 f5 Rc5 Ra4 c3 Kf6 Kf3 Ke7 e4 Kd6 exf5 gxf5 gxf5 exf5 Rxf5 Ra3 Rc5 h5 Kf4 Ra1 Rxh5 Rf1+ Ke3 Re1+ Kd3 Rd1+ Kc4 Re1 b5 Re4+ Kb3 Re8 c4 Rc8 Kb4 Ke6 c5 Kf6 c6 Kg6 Rd5 Kf6 Kc5 Ke6 b6 Rb8 Rh5 Ke7 Rh7+ Kd8 Rb7 Kc8 Rh7 Kd8 Rh8+ Ke7 Rxb8 Ke6 c7 Kd7 c8=Q+ Ke7 Rb7+ Kf6 Qc6+ Ke5 Qd5+ Kf4 h4 Kg4 h5 Kf4 h6 Kg4 h7 Kg3 h8=Q Kf4 Re7 Kg3 Qf5 Kg2 Rg7#", "id": "cV4KfET5", "rated": true, "url": "http://lichess.org/cV4KfET5/black", "status": "mate", "timestamp": 1458405999163, "winner": "white", "variant": "standard", "perf": "classical", "turns": 141, "players": {"white": {"userId": "sanch", "ratingDiff": 18, "rating": 1586}, "black": {"userId": "whiznl", "ratingDiff": -36, "rating": 1781}}}, {"speed": "classical", "clock": {"increment": 5, "initial": 300, "totalTime": 500}, "moves": "d4 c5 d5 Nf6 c4 e6 Nc3 exd5 cxd5 b6 e4 Bb7 Nf3 Bd6 e5 Bxe5 Nxe5 Qe7 Qe2 Nxd5 Nf3 Qxe2+ Bxe2 Nxc3 bxc3 O-O O-O Nc6 Bb5 a6 Ba4 b5 Bb3 c4 Bc2 d5 Nd4 Nxd4 cxd4 Bc8 Re1 Be6 Ba3 Rfe8 Re3 Rab8 Rae1 g6 Bc5 a5 a3 b4 axb4 axb4 Bd6 Rb6 Bc5 Rbb8 Ba4 Rec8 Bd6 Rb6 Bc5 Rbb8 Rb1 b3 Rc3 b2 Ba3 Bf5 Rxb2 Ra8 Bc2 Bxc2 Rbxc2 Re8 f3 Kg7 Kf2 f5 Re2 Rxe2+ Kxe2 Re8+ Kf2 f4 g3 g5 gxf4 gxf4 h4 Kf6 Kg2 Kf5 Kh3 h5 Bb2 Rb8 Rc2 Rb3 Kg2 Rd3 Re2 c3 Re5+ Kf6 Bxc3 Rxc3 Rxd5 Rc2+ Kh3 Kg6 Rd6+ Kf5 d5 Rd2 Rd8 Ke5 Rh8 Rxd5 Rxh5+ Ke6 Rxd5 Kxd5 Kg4 Ke6 Kg5 Kf7 Kxf4 Kf6 Kg4 Kg6 f4 Kf6 h5 Kg7 Kg5 Kh7 f5 Kg7 h6+ Kh8 f6 Kh7 f7 Kh8 f8=Q+ Kh7 Qg7#", "id": "QGRN5jaP", "rated": true, "url": "http://lichess.org/QGRN5jaP/black", "status": "mate", "timestamp": 1458391561124, "winner": "white", "variant": "standard", "perf": "classical", "turns": 149, "players": {"white": {"userId": "whiznl", "ratingDiff": 28, "rating": 1753, "analysis": {"blunder": 1, "mistake": 7, "inaccuracy": 5}}, "black": {"userId": "andrew_hug", "ratingDiff": -10, "rating": 1757, "analysis": {"blunder": 2, "mistake": 9, "inaccuracy": 4}}}}, {"speed": "classical", "clock": {"increment": 5, "initial": 300, "totalTime": 500}, "moves": "e4 c6 Nf3 d5 exd5 cxd5 Nc3 Bg4 Be2 Nf6 d4 e6 h3 Bh5 g4 Bg6 Nh4 Nc6 Bb5 a6 Nxg6 hxg6 Bxc6+ bxc6 Bg5 c5 Qd2 Qb6 Na4 Qa7 Qa5 cxd4 Bxf6 gxf6 O-O-O Rc8 Nb6 Rc6 Na4 d3 Rxd3 Qxf2 Nc3 Bh6+ Kb1 O-O Qa4 Rfc8 Rhd1 f5 gxf5 Qxf5 Ne2 Bg7 Ng3 Qe5 c3 Bf6 Qc2 Bh4 Ne2 Bg5 Nd4 R6c7 Nf3 Qf5 Nxg5 Qxg5 Qf2 Rb8 h4 Qh5 Rg1 Kg7 Rg5 Qh6 Rh3 f6 Rgg3 Qh7 Rf3 g5+ Ka1 g4 Rxf6 gxh3 Qg3+ Kxf6 Qg5+ Kf7", "id": "SOu6baeL", "rated": true, "url": "http://lichess.org/SOu6baeL/white", "status": "resign", "timestamp": 1458341030474, "winner": "black", "variant": "standard", "perf": "classical", "turns": 90, "players": {"white": {"userId": "hoplaaa", "ratingDiff": -13, "rating": 1814, "analysis": {"blunder": 2, "mistake": 6, "inaccuracy": 3}}, "black": {"userId": "whiznl", "ratingDiff": 39, "rating": 1714, "analysis": {"blunder": 1, "mistake": 2, "inaccuracy": 8}}}}, {"speed": "classical", "clock": {"increment": 5, "initial": 300, "totalTime": 500}, "moves": "d4 e6 c4 c5 d5 e5 Nc3 d6 e4 Be7 Nf3 Nf6 Bg5 b6 Be2 Bd7 O-O a6 Re1 h6 Bxf6 Bxf6 a3 g5 b4 g4 Nd2 h5 bxc5 bxc5 Nf1 Rg8 Ng3 h4 Nh5 Be7 f3 gxf3 Bxf3 Qc8 Ne2 Bg4 Bxg4 Qxg4 Nef4 exf4 Qxg4 Rxg4 Rf1 Rg5 Nxf4 Nd7 Rf3 Ne5 Rc1 Nxf3+", "id": "ztolKen3", "rated": true, "url": "http://lichess.org/ztolKen3/black", "status": "resign", "timestamp": 1458333053265, "winner": "black", "variant": "standard", "perf": "classical", "turns": 56, "players": {"white": {"userId": "whiznl", "ratingDiff": -24, "rating": 1738}, "black": {"userId": "hansheinz", "ratingDiff": 10, "rating": 1808}}}, {"speed": "classical", "clock": {"increment": 5, "initial": 300, "totalTime": 500}, "moves": "e4 c6 d4 d5 e5 Bf5 g4 Bg6 f4 e6 Nf3 c5 Bb5+ Nc6 Be3 a6 Bxc6+ bxc6 dxc5 Qa5+ Qd2 Qxd2+ Nbxd2 Bxc2 Bd4 Nh6 h3 Rb8 Nb3 Bxb3 axb3 Ra8 b4 Be7 Bc3 O-O Nd4 Rfc8 O-O a5 Ra3 axb4 Rxa8 Rxa8 Bxb4 Rc8 Ra1 f6 Ra6 fxe5 fxe5 Bg5 Kg2 Nf7 Nxc6 Kf8 Bc3 Bf4 Kf3 Bh2 Bd4 Ng5+ Kg2 Bf4 b4 Bd2 b5 Ne4 b6 Rxc6 b7 Rxa6 b8=Q+ Kf7 Qb7+ Kg6 Qxa6 Bb4 Qxe6+", "id": "hUhVb34s", "rated": true, "url": "http://lichess.org/hUhVb34s/black", "status": "resign", "timestamp": 1458328620445, "winner": "white", "variant": "standard", "perf": "classical", "turns": 79, "players": {"white": {"userId": "mehmetsyss", "ratingDiff": 15, "rating": 1667, "analysis": {"blunder": 0, "mistake": 2, "inaccuracy": 3}}, "black": {"provisional": true, "userId": "whiznl", "ratingDiff": -41, "rating": 1779, "analysis": {"blunder": 2, "mistake": 3, "inaccuracy": 8}}}}, {"speed": "classical", "clock": {"increment": 5, "initial": 300, "totalTime": 500}, "moves": "d4 Nf6 c4 g6 Nc3 Bg7 Nf3 d6 g3 O-O Bg2 c6 b4 Re8 a4 e5 dxe5 dxe5 Qxd8 Rxd8 Bb2 e4 Ng5 Re8 Ncxe4 Nxe4 Bxg7 Nxg5 Bf6 Ne4 Bb2 Na6 b5 cxb5 axb5 Nac5 Bd4 Be6 Bxe4 Nxe4 Rxa7 Rxa7 Bxa7 Ra8 b6 Bxc4 O-O Nc5 Rc1 Bxe2 Rxc5 Kg7 Kg2 Bd3 Rc7 Be4+ f3 Bc6 Rxc6 bxc6 b7 Rxa7 b8=Q", "id": "03Z6Cmj7", "rated": true, "url": "http://lichess.org/03Z6Cmj7/white", "status": "resign", "timestamp": 1458078162252, "winner": "white", "variant": "standard", "perf": "classical", "turns": 63, "players": {"white": {"provisional": true, "userId": "whiznl", "ratingDiff": 30, "rating": 1749, "analysis": {"blunder": 0, "mistake": 1, "inaccuracy": 2}}, "black": {"userId": "max27", "ratingDiff": -19, "rating": 1680, "analysis": {"blunder": 2, "mistake": 1, "inaccuracy": 0}}}}, {"speed": "classical", "clock": {"increment": 5, "initial": 300, "totalTime": 500}, "moves": "e4 c6 d4 d5 e5 Bf5 Nf3 e6 Nc3 c5 b3 cxd4 Qxd4 Nc6 Qa4 Qa5 Qxa5 Nxa5 Bb5+ Nc6 O-O Bxc2 Re1 a6 Bxc6+ bxc6 Na4 c5 Be3 c4 bxc4 Bxa4 cxd5 exd5 Red1 Rd8 Bd4 Bxd1", "id": "BnhFjKX4", "rated": true, "url": "http://lichess.org/BnhFjKX4/black", "status": "resign", "timestamp": 1458077873623, "winner": "black", "variant": "standard", "perf": "classical", "turns": 38, "players": {"white": {"userId": "facaamarela", "ratingDiff": -8, "rating": 1646}, "black": {"provisional": true, "userId": "whiznl", "ratingDiff": 34, "rating": 1715}}}, {"speed": "classical", "clock": {"increment": 5, "initial": 300, "totalTime": 500}, "moves": "d4 d5 c4 e6 Nc3 Nf6 Nf3 Bb4 Bg5 Nc6 a3 Bxc3+ bxc3 O-O e3 Qd6 Bxf6 gxf6 Bd3 e5 Nh4 dxc4 Bxc4 exd4 cxd4 Ne7 O-O b6 Qf3 Rb8 Bd3 f5 Nxf5 Nxf5 Bxf5 Bb7 Qh5 h6 Qg4+ Kh8 Rfc1 Rg8 Qh3 Bc8 Rxc7 Qxc7 Qxh6#", "id": "L7dccV1A", "rated": true, "url": "http://lichess.org/L7dccV1A/white", "status": "mate", "timestamp": 1458076415176, "winner": "white", "variant": "standard", "perf": "classical", "turns": 47, "players": {"white": {"provisional": true, "userId": "whiznl", "ratingDiff": 15, "rating": 1700, "analysis": {"blunder": 2, "mistake": 1, "inaccuracy": 2}}, "black": {"provisional": true, "userId": "miki673", "ratingDiff": -34, "rating": 1410, "analysis": {"blunder": 2, "mistake": 0, "inaccuracy": 6}}}}, {"speed": "classical", "clock": {"increment": 5, "initial": 300, "totalTime": 500}, "moves": "d4 e6 c4 Nf6 Nc3 Nc6 Nf3 e5 dxe5 Ng4 Bg5 f6 exf6 gxf6 Bh4 Bc5 e3 Qe7 Qd5 Bxe3 fxe3 Qxe3+ Be2 Qf2+ Bxf2 Nxf2 Kxf2 Nd4 Nxd4", "id": "sPr0t0fS", "rated": true, "url": "http://lichess.org/sPr0t0fS/white", "status": "resign", "timestamp": 1458076088005, "winner": "white", "variant": "standard", "perf": "classical", "turns": 29, "players": {"white": {"provisional": true, "userId": "whiznl", "ratingDiff": 12, "rating": 1688}, "black": {"userId": "stringerbell77", "ratingDiff": -3, "rating": 1335}}}, {"speed": "classical", "clock": {"increment": 5, "initial": 300, "totalTime": 500}, "moves": "d4 f6 e4 g5 Qh5#", "id": "HQFOJbC2", "rated": true, "url": "http://lichess.org/HQFOJbC2/white", "status": "mate", "timestamp": 1458076017966, "winner": "white", "variant": "standard", "perf": "classical", "turns": 5, "players": {"white": {"provisional": true, "userId": "whiznl", "ratingDiff": 13, "rating": 1675}, "black": {"userId": "stringerbell77", "ratingDiff": -4, "rating": 1339}}}, {"speed": "classical", "clock": {"increment": 5, "initial": 300, "totalTime": 500}, "moves": "d4 d5 c4 e6 Nc3 Nf6 Nf3 c5 Bg5 cxd4 Nxd4 Bc5 e3 Nc6 b3 O-O Be2 h6 Bh4 Nxd4 exd4 Bb4 Qc2 Qa5 Rc1 Ne4 O-O Nxc3 a4 Nxe2+ Qxe2 Qb6 Qe3 Qa5 Rcd1 Re8 Rd3 Be7 Bg3 dxc4 bxc4 Qxa4 c5 Bg5 Bf4 Bxf4 Qxf4 e5 Qe4 g6 Qh4 Kg7 Re1 Bf5 Rdd1 exd4 Kf1 Rxe1+ Rxe1 g5 Qg3 Kg6 Qd6+ Kh5 h3 Bxh3 gxh3 Qc6 Qxd4 Qh1+ Ke2 Qc6 Qg4+ Kg6 Qe4+ f5 Qc4 Re8+ Kd2 Rxe1 Kxe1 Kh5 Qf7+ Qg6 Qxb7 g4 hxg4+ Qxg4 Qf7+ Kh4 Qxa7 Qe4+ Kd2 Qf4+ Ke2 Kh3 c6 Qe4+ Kf1 Qxc6 Qe3+ Kh2 Qxh6+ Qxh6 f4 Qxf4+ Ke2 Qe4+", "id": "c91uiNuj", "rated": true, "url": "http://lichess.org/c91uiNuj/white", "status": "resign", "timestamp": 1457985918197, "winner": "black", "variant": "standard", "perf": "classical", "turns": 108, "players": {"white": {"userId": "agerman", "ratingDiff": -11, "rating": 1654}, "black": {"provisional": true, "userId": "whiznl", "ratingDiff": 61, "rating": 1614}}}, {"speed": "classical", "clock": {"increment": 5, "initial": 300, "totalTime": 500}, "moves": "e4 c6 Nf3 d5 exd5 cxd5 c3 Nc6 d4 Bg4 Bb5 a6 Ba4 b5 Bc2 e6 O-O Be7 h3 Bxf3 Qxf3 Nf6 Re1 O-O Nd2 b4 Nf1 Rb8 Ng3 h6 Nh5 bxc3 bxc3 Re8 Ba4 Rc8 Rb1 Qa5 Bb3 Nxd4 cxd4 Qxe1+ Kh2 Qe4 Qxe4 Nxe4 Be3 Rb8 Bc2 Rxb1 Bxb1 Bg5 Bxe4 Bxe3 Bd3 Bxf2 g4 Bxd4 a4 a5 Bb5 Rc8 Kg3 Be5+ Kf3 g6 Ng3 Bxg3 Kxg3", "id": "gPCTTczo", "rated": true, "url": "http://lichess.org/gPCTTczo/black", "status": "resign", "timestamp": 1457985096413, "winner": "black", "variant": "standard", "perf": "classical", "turns": 69, "players": {"white": {"provisional": true, "userId": "hexagone", "ratingDiff": -16, "rating": 1365}, "black": {"provisional": true, "userId": "whiznl", "ratingDiff": 28, "rating": 1586}}}, {"speed": "classical", "clock": {"increment": 5, "initial": 300, "totalTime": 500}, "moves": "d4 d5 c4 Nf6 cxd5 Nxd5 Nf3 e6 a3 Bd6 Nc3 O-O e4 Nxc3 bxc3 Re8 Bb5 c6 Ba4 e5 dxe5 Bc7 Qxd8 Rxd8 Bg5 Re8 Bf4 Ba5 Rc1 Na6 Be3 b5 Bb3 c5 Bd5 Rb8 Ng5 Be6 Nxe6 fxe6 Bc6 Rec8 Bd7 b4 Bxc8 Rxc8 axb4 cxb4 O-O bxc3 Bxa7 Nb4 Bd4 Nd3 Rc2 Nb4 Rxc3 Na6 Rxc8+", "id": "PXDqoI8R", "rated": true, "url": "http://lichess.org/PXDqoI8R/black", "status": "resign", "timestamp": 1457907916562, "winner": "white", "variant": "standard", "perf": "classical", "turns": 59, "players": {"white": {"provisional": true, "userId": "whiznl", "ratingDiff": 96, "rating": 1490, "analysis": {"blunder": 1, "mistake": 2, "inaccuracy": 2}}, "black": {"userId": "brochess", "ratingDiff": -18, "rating": 1631, "analysis": {"blunder": 3, "mistake": 4, "inaccuracy": 0}}}}, {"speed": "classical", "clock": {"increment": 5, "initial": 300, "totalTime": 500}, "moves": "d4 d5 c4 dxc4 e3 Nc6 Bxc4 Nf6 Nf3 Ne4 Nc3 Bf5 O-O e5 dxe5 f6 exf6 gxf6 Qxd8+ Kxd8 Nxe4 Bxe4 Rd1+ Bd6 Nd4 Nxd4 Rxd4 Re8 f3 Bf5 Bf7 c5 Bxe8 cxd4 exd4 Kxe8 b3 Rd8 Bb2 Rd7 d5 Kf7 g4 Bd3 Rd1 Be5 Bxe5 fxe5 Rxd3 b5 Kg2 Ke7 h4 Kd6 h5 Rc7 a4 b4 g5 a5 Kg3 Rc3 g6 hxg6 hxg6 Rc8 Kg4 Ke7 Kf5 Kf8 Kxe5 Rc3 Ke4 Kg7 d6 Kxg6 d7 Rxd3 Kxd3 Kg5 d8=Q+ Kf4 Qxa5 Kxf3 Kc4 Ke4 Qd5+ Ke3 a5", "id": "uXlgGG5L", "rated": true, "url": "http://lichess.org/uXlgGG5L/white", "status": "outoftime", "timestamp": 1457906809281, "winner": "white", "variant": "standard", "perf": "classical", "turns": 89, "players": {"white": {"provisional": true, "userId": "whiznl", "ratingDiff": 57, "rating": 1433, "analysis": {"blunder": 2, "mistake": 2, "inaccuracy": 12}}, "black": {"userId": "burak3636", "ratingDiff": -9, "rating": 1316, "analysis": {"blunder": 2, "mistake": 10, "inaccuracy": 5}}}}, {"speed": "classical", "clock": {"increment": 5, "initial": 300, "totalTime": 500}, "moves": "e4 c6 d4 d5 exd5 cxd5 Nc3 Nc6 Qf3 Nf6 Nge2 Bg4 Qe3 e6 f3 Bf5 Nf4 Bxc2 Bb5 a6 Bxc6+ bxc6 Bd2 Qb6 Rb1 Bxb1 Nxb1 Qxb2 Nxe6 Qxb1+ Bc1 fxe6 Qxe6+ Be7 Kf2 Qxa2+ Kg3 Qa4 Re1 Qb4 Qxc6+ Kf7 Qe6+ Kg6 h4 h5 Bd2 Qxd2 Qxe7 Qxd4 Re6 Rhe8 Qd6 Rxe6 Qxe6 a5 Qe1 a4 Qf2 Qe5+ f4 Ne4+ Kf3 Nxf2 fxe5 Nd3 e6 Kf6 Ke2 Kxe6 Kxd3 a3 Kc2 a2 g4 a1=Q gxh5 Qd4 h6 gxh6", "id": "K2bD4Cza", "rated": true, "url": "http://lichess.org/K2bD4Cza/black", "status": "resign", "timestamp": 1457905967387, "winner": "black", "variant": "standard", "perf": "classical", "turns": 80, "players": {"white": {"userId": "burak3636", "ratingDiff": -11, "rating": 1327}, "black": {"provisional": true, "userId": "whiznl", "ratingDiff": 102, "rating": 1331}}}, {"speed": "classical", "clock": {"increment": 5, "initial": 300, "totalTime": 500}, "moves": "d4 d5 c4 e6 Nc3 Bb4 Nf3 Bxc3+ bxc3 dxc4 e3 b5 a4 Bd7 axb5 Bxb5 Ne5 f6 Bxc4 Bxc4 Nxc4 Ne7 Ba3 O-O O-O Re8 Bb4 Nd5 Qb3 Nc6 Rfc1 Ncxb4 cxb4 c6 b5 cxb5 Qxb5 Rb8 Qa6 Nb4 Qxa7 Ra8 Qb6 Rb8 Qxd8 Rexd8 Rcb1 Rdc8 Nd6 Rc2 Ra4 Rc6 Rbxb4 Rxb4 Rxb4 Rxd6 f3 Kf7 Kf2 g5 Ke2 Rc6 Kd3 Rc1 h3 Rh1 f4 h6 fxg5 hxg5 e4 Rg1 g4 Rg3+ Kc4 Rxh3 d5 exd5+ exd5 Rh4 Kc5 f5 d6 f4 Rb3 Rh8 Rb7+ Ke6 d7 Rd8 Kc6 f3 Rb2 Rxd7 Rf2 Rd3 Kc5 Ke5 Kc4 Ra3 Kb4 Re3 Kc4 Kf4 Kd4 Ra3 Kc4 Kxg4", "id": "5omcfl6A", "rated": true, "url": "http://lichess.org/5omcfl6A/black", "status": "resign", "timestamp": 1457902538455, "winner": "black", "variant": "standard", "perf": "classical", "turns": 108, "players": {"white": {"provisional": true, "userId": "whiznl", "ratingDiff": -71, "rating": 1402, "analysis": {"blunder": 9, "mistake": 4, "inaccuracy": 3}}, "black": {"userId": "rickveg", "ratingDiff": 6, "rating": 1575, "analysis": {"blunder": 9, "mistake": 3, "inaccuracy": 3}}}}, {"speed": "classical", "clock": {"increment": 5, "initial": 300, "totalTime": 500}, "moves": "d4 d5 c4 e6 Nc3 Bb4 Nf3 Nf6 e3 Nc6 a3 Bxc3+ bxc3 h6 cxd5 exd5 Bb5 O-O O-O Bd7 h3 a6 Ba4 b5 Bb3 Be6 Re1 Na5 a4 Nc4 axb5 axb5 Rxa8 Qxa8 Nd2 Nxd2 Bxd2 Ne4 f3 Ng3 Kh2 Nh5 g4 Nf6 e4 dxe4 Bxe6 fxe6 fxe4 Nxe4 Qe2 Rf2+", "id": "IBM3xhK8", "rated": true, "url": "http://lichess.org/IBM3xhK8/black", "status": "resign", "timestamp": 1457902000007, "winner": "black", "variant": "standard", "perf": "classical", "turns": 52, "players": {"white": {"provisional": true, "userId": "whiznl", "ratingDiff": -98, "rating": 1500}, "black": {"userId": "filorly", "ratingDiff": 5, "rating": 1686}}}]}